[{"src": [["광주시/NNP", "광산구/NNP", "가/JKS", "지나/VV", "ㄴ/ETM", "1/SN", "월/NNB", "자체/NNG", "실시/NNG", "하/XSV", "ㄴ/ETM", "‘/SS", "시민/NNG", "안전/NNG", "만족/NNG", "도/NNG", "조사/NNG", "’/SS", "에서/JKB", "정책/NNG", "과/JC", "민원/NNG", "처리/NNG", "만족/NNG", "도/NNG", ",/SP", "체감/NNG", "도/NNG", "등/NNB", "안전/NNG", "전/MM", "분야/NNG", "에서/JKB", "긍정/NNG", "평가/NNG", "를/JKO", "받/VV", "었/EP", "다/EF"], ["‘/SS", "나/NP", "의/JKG", "삶/NNG", "을/JKO", "바꾸/VV", "는/ETM", "안전/NNG", "광산/NNG", "프로젝트/NNG", "’/SS", "의/JKG", "하나/NNG", "로/JKB", "실시/NNG", "하/XSV", "ㄴ/ETM", "이/MM", "조사/NNG", "는/JX", "안전/NNG", "수요/NNG", "자/XSN", "이/VCP", "ㄴ/ETM", "시민/NNG", "이/JKS", "피부/NNG", "로/JKB", "느끼/VV", "는/ETM", "만족/NNG", "도/NNG", "등/NNB", "을/JKO", "파악/NNG", "하/XSV", "어/EC", "구/NNG", "안전/NNG", "정책/NNG", "의/JKG", "실태/NNG", "를/JKO", "진단/NNG", "하/XSV", "고/EC", "실용적/MM", "정책/NNG", "개발/NNG", "등/NNB", "에/JKB", "기초/NNG", "자료/NNG", "로/JKB", "활용/NNG", "하/XSV", "기/ETN", "위하/VV", "어/EC", "이뤄지/VV", "었/EP", "다/EF"], ["광산구/NNP", "는/JX", "성/NNG", "·/SP", "연령/NNG", "·/SP", "지역/NNG", "을/JKO", "안배/NNG", "하/XSV", "어/EC", "전자/NNG", "설문/NNG", "방식/NNG", "을/JKO", "도입/NNG", ",/SP", "총/MM", "1/SN", "천/NR", "107/SN", "명/NNB", "의/JKG", "응답/NNG", "을/JKO", "얻/VV", "었/EP", "다/EF"], ["안전/NNG", "정책/NNG", "분야/NNG", "별/XSN", "만족/NNG", "도/NNG", "는/JX", "재난/NNG", "재해/NNG", "대응/NNG", "체계/NNG", "(/SS", "632/SN", "%/SW", ")/SS", ",/SP", "예방/NNG", "투자/NNG", "(/SS", "618/SN", "%/SW", ")/SS", ",/SP", "취약/NNG", "계층/NNG", "지원/NNG", "정책/NNG", "(/SS", "609/SN", "%/SW", ")/SS", "순/NNB", "이/VCP", "었/EP", "다/EF"], ["반면/NNG", ",/SP", "‘/SS", "안전/NNG", "정책/NNG", "의/JKG", "종합/NNG", "만족/NNG", "도/NNG", "’/SS", "와/JC", "‘/SS", "민원/NNG", "처리/NNG", "신속/NNG", "성/XSN", "’/SS", "은/JX", "각각/MAG", "597/SN", "%/SW", "로/JKB", "상대/NNG", "적/XSN", "으로/JKB", "시민/NNG", "의/JKG", "기대/NNG", "치/XSN", "에/JKB", "못/MAG", "미치/VV", "는/ETM", "것/NNB", "으로/JKB", "나타나/VV", "었/EP", "다/EF"], ["//SP", "광산/NNG", "=/SW", "고훈석/NNP", "기자/NNG"]], "tgt": [["광주시/NNP", "광산구/NNP", "가/JKS", "지나/VV", "ㄴ/ETM", "1/SN", "월/NNB", "자체/NNG", "실시/NNG", "하/XSV", "ㄴ/ETM", "‘/SS", "시민/NNG", "안전/NNG", "만족/NNG", "도/NNG", "조사/NNG", "’/SS", "에서/JKB", "정책/NNG", "과/JC", "민원/NNG", "처리/NNG", "만족/NNG", "도/NNG", ",/SP", "체감/NNG", "도/NNG", "등/NNB", "안전/NNG", "전/MM", "분야/NNG", "에서/JKB", "긍정/NNG", "평가/NNG", "를/JKO", "받/VV", "었/EP", "다/EF"], ["‘/SS", "나/NP", "의/JKG", "삶/NNG", "을/JKO", "바꾸/VV", "는/ETM", "안전/NNG", "광산/NNG", "프로젝트/NNG", "’/SS", "의/JKG", "하나/NNG", "로/JKB", "실시/NNG", "하/XSV", "ㄴ/ETM", "이/MM", "조사/NNG", "는/JX", "안전/NNG", "수요/NNG", "자/XSN", "이/VCP", "ㄴ/ETM", "시민/NNG", "이/JKS", "피부/NNG", "로/JKB", "느끼/VV", "는/ETM", "만족/NNG", "도/NNG", "등/NNB", "을/JKO", "파악/NNG", "하/XSV", "어/EC", "구/NNG", "안전/NNG", "정책/NNG", "의/JKG", "실태/NNG", "를/JKO", "진단/NNG", "하/XSV", "고/EC", "실용적/MM", "정책/NNG", "개발/NNG", "등/NNB", "에/JKB", "기초/NNG", "자료/NNG", "로/JKB", "활용/NNG", "하/XSV", "기/ETN", "위하/VV", "어/EC", "이뤄지/VV", "었/EP", "다/EF"], ["//SP", "광산/NNG", "=/SW", "고훈석/NNP", "기자/NNG"]]}, {"src": [["공간/NNG", "장기/NNG", "무상/NNG", "임차/NNG", "예산/NNG", "절감/NNG"], ["광주시/NNP", "광산구/NNP", "가/JKS", "최근/NNG", "구립/NNG", "어린이/NNG", "집/NNG", "2/SN", "곳/NNG", "을/JKO", "개원/NNG", "하/XSV", "고/EC", "공공/NNG", "보육/NNG", "서비스/NNG", "를/JKO", "강화/NNG", "하/XSV", "ㄴ다/EF"], ["광주시/NNP", "광산구/NNP", "가/JKS", "지나/VV", "ㄴ/ETM", "12/SN", "일/NNB", "구립/NNG", "장자울/NNP", "어린이/NNG", "집/NNG", "과/JC", "꿈/NNG", "엽/VA", "ㄹ/ETM", "어린이/NNG", "집/NNG", "개원/NNG", "식/XSN", "을/JKO", "갖/VV", "고/EC", "본격/NNG", "운영/NNG", "에/JKB", "들어가/VV", "었/EP", "다/EF"], ["두/MM", "구립/NNG", "어린이/NNG", "집/NNG", "은/JX", "부모/NNG", "가/JKS", "안심/NNG", "하/XSV", "고/EC", "맡기/VV", "ㄹ/ETM", "수/NNB", "있/VA", "는/ETM", "보육/NNG", "환경/NNG", "조성/NNG", "과/JC", "양질/NNG", "의/JKG", "보육/NNG", "서비스/NNG", "제공/NNG", "을/JKO", "위하/VV", "어/EC", "광산/NNP", "구/NNG", "가/JKS", "신규/NNG", "설치/NNG", "하/XSV", "ㄴ/ETM", "곳/NNG", "이/VCP", "다/EF"], ["장자울/NNP", "어린이/NNG", "집/NNG", "은/JX", "수완동/NNP", "장자울마을/NNP", "아파트/NNG", "휴먼시아/NNP", "4/SN", "단지/NNG", "관리/NNG", "동/NNG", "에/JKB", "자리/NNG", "를/JKO", "잡/VV", "었/EP", "다/EF"], ["꿈엽/VA", "ㄹ/ETM", "어린이/NNG", "집/NNG", "은/JX", "하남동/NNP", "산정/NNG", "빛여울채/NNP", "아파트/NNG", "관리/NNG", "동/NNG", "에/JKB", "있/VA", "다/EF"], ["지난해/NNG", "4/SN", "월/NNB", "수완동/NNP", "에/JKB", "직영/NNG", "구립/NNG", "어린이/NNG", "집/NNG", "을/JKO", "개원/NNG", "하/XSV", "ㄴ/ETM", "광산구/NNP", "는/JX", "이번/NNG", "2/SN", "곳/NNG", "의/JKG", "어린이/NNG", "집/NNG", "설립/NNG", "예산/NNG", "을/JKO", "아끼/VV", "었/EP", "다/EF"], ["광산구/NNP", "는/JX", "교직/NNG", "원/XSN", "에게/JKB", "구립/NNG", "어린이/NNG", "집/NNG", "1/SN", "호/NNB", "운영/NNG", "으로/JKB", "쌓이/VV", "ㄴ/ETM", "보육/NNG", "전문/NNG", "지식/NNG", "과/JC", "경험/NNG", "도/JX", "공유/NNG", "하/XSV", "ㄹ/ETM", "계획/NNG", "이/VCP", "다/EF"], ["김삼호/NNP", "광산/NNG", "구청/NNG", "장/XSN", "은/JX", "“/SS", "구립/NNG", "어린이/NNG", "집/NNG", "으로/JKB", "보육/NNG", "의/JKG", "공공/NNG", "성/XSN", "강화/NNG", "모델/NNG", "을/JKO", "정립/NNG", "하/XSV", "고/EC", "국/NNG", "공립/NNG", "어린이집/NNG", "확충/NNG", "으로/JKB", "지역/NNG", "사회/NNG", "와/JKB", "함께/MAG", "공공/NNG", "보육/NNG", "을/JKO", "꾸준히/MAG", "확대/NNG", "하/XSV", "겠/EP", "다/EF", "”/SS", "고/JKQ", "밝히/VV", "었/EP", "다/EF"], ["광산/NNG", "=/SW", "고훈석/NNP", "기자/NNG"]], "tgt": [["광주시/NNP", "광산구/NNP", "가/JKS", "지나/VV", "ㄴ/ETM", "12/SN", "일/NNB", "구립/NNG", "장자울/NNP", "어린이/NNG", "집/NNG", "과/JC", "꿈/NNG", "엽/VA", "ㄹ/ETM", "어린이/NNG", "집/NNG", "개원/NNG", "식/XSN", "을/JKO", "갖/VV", "고/EC", "본격/NNG", "운영/NNG", "에/JKB", "들어가/VV", "었/EP", "다/EF"], ["꿈엽/VA", "ㄹ/ETM", "어린이/NNG", "집/NNG", "은/JX", "하남동/NNP", "산정/NNG", "빛여울채/NNP", "아파트/NNG", "관리/NNG", "동/NNG", "에/JKB", "있/VA", "다/EF"]]}, {"src": [["김삼호/NNP", "광주/NNP", "광산/NNG", "구청/NNG", "장/XSN", "이/JKS", "지난달/NNG", "19/SN", "일/NNB", "부터/JX", "이달/NNG", "7/SN", "일/NNB", "까지/JX", "17/SN", "일/NNB", "간/XSN", "21/SN", "개/NNB", "동/NNG", "을/JKO", "돌/VV", "며/EC", "시민/NNG", "과/JKB", "함께/MAG", "마을/NNG", "현안/NNG", "을/JKO", "논의/NNG", "하/XSV", "고/EC", "해결/NNG", "책/XSN", "을/JKO", "마련/NNG", "하/XSV", "는/ETM", "‘/SS", "매력/NNG", "·/SP", "활력/NNG", "·/SP", "품격/NNG", "의/JKG", "마을/NNG", "정부/NNG", "소통/NNG", "투어/NNG", "’/SS", "를/JKO", "가지/VV", "었/EP", "다/EF"], ["이번/NNG", "마을/NNG", "정부/NNG", "투어/NNG", "에서/JKB", "접수/NNG", "되/XSV", "ㄴ/ETM", "주민/NNG", "제안/NNG", "은/JX", "총/MM", "147/SN", "건/NNB", "으로/JKB", "이/MM", "중/NNB", "약/MM", "58/SN", "%/SW", "가/JKS", "안전/NNG", "관련/NNG", "사안/NNG", "이/VCP", "었/EP", "다/EF"], ["올해/NNG", "신년/NNG", "사/XSN", "에서/JKB", "안전/NNG", "하/XSA", "ㄴ/ETM", "환경/NNG", "으로/JKB", "시민/NNG", "이/JKS", "편안/NNG", "하/XSA", "ㄴ/ETM", "일상/NNG", "을/JKO", "만들/VV", "겠/EP", "다고/EC", "밝히/VV", "ㄴ/ETM", "김/NNP", "구청/NNG", "장/XSN", "은/JX", "제안/NNG", "중/NNB", "시민/NNG", "안전/NNG", "과/JKB", "직결/NNG", "되/XSV", "는/ETM", "사항/NNG", "은/JX", "빠르/VA", "ㄴ/ETM", "시일/NNG", "안/NNG", "에/JKB", "즉시/NNG", "조치/NNG", "하/XSV", "ㄹ/ETM", "방침/NNG", "이/VCP", "다/EF"], ["이번/NNG", "투어/NNG", "는/JX", "시민/NNG", "스스로/MAG", "지역/NNG", "과/JC", "마을/NNG", "의/JKG", "현안/NNG", "을/JKO", "공론/NNG", "화/XSN", "하/XSV", "고/EC", "집단/NNG", "지성/NNG", "으로/JKB", "문제/NNG", "의/JKG", "해결/NNG", "책/XSN", "을/JKO", "제시/NNG", "하/XSV", "ㄴ/ETM", "참여/NNG", "의/JKG", "장/NNG", "이/VCP", "자/EC", "실질/NNG", "적/XSN", "이/VCP", "ㄴ/ETM", "소통/NNG", "공간/NNG", "이/VCP", "었/EP", "다/EF"], ["구체/NNG", "적/XSN", "으로/JKB", "지난달/NNG", "26/SN", "일/NNB", "‘/SS", "3/SN", "安/SH", "(/SS", "안/NNG", ")/SS", "마을/NNG", "만들/VV", "기/ETN", "프로젝트/NNG", "’/SS", "를/JKO", "주제/NNG", "로/JKB", "내걸/VV", "ㄴ/ETM", "송정/NNP", "1/SN", "동/NNG", "주민/NNG", "들/XSN", "은/JX", "‘/SS", "안전/NNG", "하/XSA", "어/EC", ",/SP", "안심/NNG", "되/XSV", "고/EC", ",/SP", "모두/NNG", "가/JKS", "안락/NNG", "하/XSA", "ㄴ/ETM", "생활/NNG", "’/SS", "에/JKB", "대하/VV", "어/EC", "토론/NNG", "하/XSV", "었/EP", "다/EF"], ["신창동/NNP", "주민/NNG", "들/XSN", "은/JX", "이달/NNG", "4/SN", "일/NNB", "라디오/NNG", "송신/NNG", "탑/NNG", "이전/NNG", "부지/NNG", "활용/NNG", "방안/NNG", "에/JKB", "대하/VV", "어/EC", "고민/NNG", "하/XSV", "었/EP", "다/EF"], ["같/VA", "은/ETM", "달/NNG", "7/SN", "일/NNB", "첨단/NNG", "1/SN", "동/NNG", "주민/NNG", "들/XSN", "은/JX", "‘/SS", "골목/NNG", "상권/NNG", "활성/NNG", "화/XSN", "’/SS", "를/JKO", "토론/NNG", "주제/NNG", "로/JKB", "올리/VV", "었/EP", "다/EF"], ["김/NNP", "구청/NNG", "장/XSN", "은/JX", "“/SS", "마을/NNG", "정부/NNG", "투어/NNG", "를/JKO", "계기/NNG", "로/JKB", "시민/NNG", "이/JKS", "스스로/MAG", "삶/NNG", "을/JKO", "바꾸/VV", "어/EC", "나가/VX", "는/ETM", "소통/NNG", "과/JC", "토론/NNG", "의/JKG", "장/NNG", "을/JKO", "더/MAG", "많이/MAG", "만들/VV", "고/EC", "이렇/VA", "게/EC", "열리/VV", "ㄴ/ETM", "공간/NNG", "에서/JKB", "더/MAG", "깊/VA", "은/ETM", "대화/NNG", "로/JKB", "지역/NNG", "의/JKG", "일/NNG", "을/JKO", "하나/NR", "씩/XSN", "해결/NNG", "하/XSV", "겠/EP", "다/EF", "”/SS", "고/JKQ", "밝히/VV", "었/EP", "다/EF"], ["광산/NNG", "=/SW", "고훈석/NNP", "기자/NNG"]], "tgt": [["김삼호/NNP", "광주/NNP", "광산/NNG", "구청/NNG", "장/XSN", "이/JKS", "지난달/NNG", "19/SN", "일/NNB", "부터/JX", "이달/NNG", "7/SN", "일/NNB", "까지/JX", "17/SN", "일/NNB", "간/XSN", "21/SN", "개/NNB", "동/NNG", "을/JKO", "돌/VV", "며/EC", "시민/NNG", "과/JKB", "함께/MAG", "마을/NNG", "현안/NNG", "을/JKO", "논의/NNG", "하/XSV", "고/EC", "해결/NNG", "책/XSN", "을/JKO", "마련/NNG", "하/XSV", "는/ETM", "‘/SS", "매력/NNG", "·/SP", "활력/NNG", "·/SP", "품격/NNG", "의/JKG", "마을/NNG", "정부/NNG", "소통/NNG", "투어/NNG", "’/SS", "를/JKO", "가지/VV", "었/EP", "다/EF"], ["올해/NNG", "신년/NNG", "사/XSN", "에서/JKB", "안전/NNG", "하/XSA", "ㄴ/ETM", "환경/NNG", "으로/JKB", "시민/NNG", "이/JKS", "편안/NNG", "하/XSA", "ㄴ/ETM", "일상/NNG", "을/JKO", "만들/VV", "겠/EP", "다고/EC", "밝히/VV", "ㄴ/ETM", "김/NNP", "구청/NNG", "장/XSN", "은/JX", "제안/NNG", "중/NNB", "시민/NNG", "안전/NNG", "과/JKB", "직결/NNG", "되/XSV", "는/ETM", "사항/NNG", "은/JX", "빠르/VA", "ㄴ/ETM", "시일/NNG", "안/NNG", "에/JKB", "즉시/NNG", "조치/NNG", "하/XSV", "ㄹ/ETM", "방침/NNG", "이/VCP", "다/EF"]]}, {"src": [["광주송정/NNP", "역세/NNG", "권/XSN", "발전/NNG", "방향/NNG", "수립/NNG", "토론/NNG", "회/XSN", "성료/NNG"], ["지나/VV", "ㄴ/ETM", "1/SN", "월/NNB", "금호타이어/NNP", "가/JKS", "광주/NNP", "공장/NNG", "이전/NNG", "의사/NNG", "를/JKO", "밝히/VV", "ㄴ/ETM", "뒤/NNG", "이뤄지/VV", "ㄴ/ETM", "이날/NNG", "토론/NNG", "회/XSN", "는/JX", "전문/NNG", "가/XSN", "와/JC", "주민/NNG", "이/JKS", "참가/NNG", "하/XSV", "어/EC", "이전/NNG", "부지/NNG", "활용/NNG", "및/MAJ", "광주/NNP", "송정/NNP", "역세/NNG", "권/XSN", "발전/NNG", "방안/NNG", "을/JKO", "모색/NNG", "하/XSV", "는/ETM", "자리/NNG", "로/JKB", "이인성/NNP", "서울시립대/NNP", "교수/NNG", "가/JKS", "진행/NNG", "을/JKO", "맡/VV", "었/EP", "다/EF"], ["첫/MM", "발제/NNG", "자/XSN", "로/JKB", "나서/VV", "ㄴ/ETM", "류영국/NNP", "지오시티/NNP", "㈜/SW", "대표/NNG", "이사/NNG", "는/JX", "‘/SS", "금호타이어/NNP", "이전/NNG", "부지/NNG", "의/JKG", "토지/NNG", "이용/NNG", "계획/NNG", "및/MAJ", "개발/NNG", "방안/NNG", "’/SS", "에서/JKB", "광주송정/NNP", "역세/NNG", "권/XSN", "의/JKG", "‘/SS", "대중/NNG", "교통/NNG", "지향/NNG", "형/XSN", "(/SS", "TOD/SL", ")/SS", "’/SS", "개발/NNG", "을/JKO", "강조/NNG", "하/XSV", "었/EP", "다/EF"], ["이어/MAG", "‘/SS", "선진/NNG", "역세/NNG", "권/XSN", "토지/NNG", "활용/NNG", "사례/NNG", "’/SS", "를/JKO", "발제/NNG", "하/XSV", "ㄴ/ETM", "박태원/NNP", "광운대/NNP", "교수/NNG", "는/JX", "“/SS", "역세/NNG", "권/XSN", "하나/NR", "잘/MAG", "키우/VV", "면/EC", "도시/NNG", "붐/NNG", "업/NNG", "과/JC", "활성/NNG", "화/XSN", "의/JKG", "기반/NNG", "을/JKO", "마련/NNG", "하/XSV", "ㄹ/ETM", "수/NNB", "있/VA", "다/EF", "”/SS", "며/EC", "“/SS", "광주/NNP", "의/JKG", "특징/NNG", "을/JKO", "잘/MAG", "보이/VV", "어/EC", "주/VX", "ㄹ/ETM", "수/NNB", "있/VA", "는/ETM", "‘/SS", "빛세/NNG", "권/XSN", "·/SP", "맛세/NNG", "권/XSN", "·/SP", "멋세/NNG", "권/XSN", "’/SS", "으로/JKB", "광주송정/NNP", "역세/NNG", "권/XSN", "을/JKO", "꾸미/VV", "어/EC", "보/VX", "기/ETN", "ㄹ/JKO", "제안/NNG", "하/XSV", "ㄴ다/EF", "”/SS", "고/JKQ", "강조/NNG", "하/XSV", "었/EP", "다/EF"], ["나아가/VV", "어/EC", "홍콩/NNP", "구룡역/NNP", ",/SP", "일본/NNP", "시나가와/NNP", ",/SP", "영국/NNP", "리버풀/NNP", ",/SP", "프랑스/NNP", "리옹/NNP", "등/NNB", "의/JKG", "역세/NNG", "권/XSN", "성공/NNG", "사례/NNG", "도/JX", "소개/NNG", "하/XSV", "었/EP", "다/EF"], ["토론/NNG", "에/JKB", "나서/VV", "ㄴ/ETM", "김성/NNP", "도/JX", "광산/NNG", "발전/NNG", "단체/NNG", "장/XSN", "협의회/NNG", "특별/NNG", "위원/NNG", "회/XSN", "위원/NNG", "장/XSN", "은/JX", "▲/SW", "금호타이어/NNP", "광주/NNP", "공장/NNG", "광산구/NNP", "내/NNB", "이전/NNG", "▲/SW", "광주송정역/NNP", "주차/NNG", "장/XSN", "확보/NNG", "▲/SW", "역세/NNG", "권/XSN", "주변/NNG", "개발/NNG", "주민/NNG", "참여/NNG", "TF/SL", "팀/NNG", "구성/NNG", "▲/SW", "광천터미널/NNP", "광주송정/NNP", "역세/NNG", "권/XSN", "이전/NNG", "등/NNB", "6/SN", "개/NNB", "의/JKG", "주민/NNG", "의견/NNG", "을/JKO", "전달/NNG", "하/XSV", "었/EP", "다/EF"], ["조강조/NNP", "금호타이어/NNP", "광주/NNP", "공장/NNG", "공장/NNG", "장/XSN", "은/JX", "“/SS", "준공/NNG", "45/SN", "년/NNB", "되/VV", "ㄴ/ETM", "공장/NNG", "주변/NNG", "환경/NNG", "변화/NNG", ",/SP", "회사/NNG", "최대/NNG", "주주/NNG", "변경/NNG", "및/MAJ", "설비/NNG", "투자/NNG", "계획/NNG", "에/JKB", "맞추/VV", "어/EC", "광주/NNP", "공장/NNG", "이전/NNG", "의/JKG", "필요/NNG", "성/XSN", "이/JKS", "대두/NNG", "되/XSV", "었/EP", "다/EF", "”/SS", "며/EC", "“/SS", "공장/NNG", "부지/NNG", "포함/NNG", ",/SP", "1/SN", "조/NR", "원/NNB", "의/JKG", "이전/NNG", "비용/NNG", "이/JKS", "필요/NNG", "하/XSA", "ㄹ/ETM", "것/NNB", "으로/JKB", "보이/VV", "ㄴ다/EF", "”/SS", "고/JKQ", "말/NNG", "하/XSV", "었/EP", "다/EF"], ["김삼호/NNP", "광산/NNG", "구청/NNG", "장/XSN", "은/JX", "“/SS", "도시/NNG", "계획/NNG", "은/JX", "도시/NNG", "민/XSN", "의/JKG", "삶/NNG", "을/JKO", "향상/NNG", "하/XSV", "고/EC", "경제/NNG", "에/JKB", "활력/NNG", "을/JKO", "불어넣/VV", "고/EC", "지속/NNG", "가능/NNG", "하/XSA", "ㄴ/ETM", "발전/NNG", "의/JKG", "관점/NNG", "을/JKO", "가지/VV", "어야/EC", "하/VX", "ㄴ다/EF", "”/SS", "며/EC", "“/SS", "도시/NNG", "공간/NNG", "을/JKO", "바꾸/VV", "려면/EC", "시민/NNG", "공감/NNG", "대/XSN", "형성/NNG", "이/JKS", "가장/MAG", "중요/NNG", "하/XSA", "고/EC", "오늘/NNG", "토론/NNG", "회/XSN", "를/JKO", "계기/NNG", "로/JKB", "광주송정/NNP", "역세/NNG", "권/XSN", "개발/NNG", "방안/NNG", "논의/NNG", "에/JKB", "탄력/NNG", "이/JKS", "붙기/VV", "ㄹ/ETM", "기대/NNG", "하/XSV", "ㄴ다/EF", "”/SS", "고/JKQ", "밝히/VV", "었/EP", "다/EF"], ["광산/NNG", "=/SW", "고훈석/NNP", "기자/NNG"]], "tgt": [["이어/MAG", "‘/SS", "선진/NNG", "역세/NNG", "권/XSN", "토지/NNG", "활용/NNG", "사례/NNG", "’/SS", "를/JKO", "발제/NNG", "하/XSV", "ㄴ/ETM", "박태원/NNP", "광운대/NNP", "교수/NNG", "는/JX", "“/SS", "역세/NNG", "권/XSN", "하나/NR", "잘/MAG", "키우/VV", "면/EC", "도시/NNG", "붐/NNG", "업/NNG", "과/JC", "활성/NNG", "화/XSN", "의/JKG", "기반/NNG", "을/JKO", "마련/NNG", "하/XSV", "ㄹ/ETM", "수/NNB", "있/VA", "다/EF", "”/SS", "며/EC", "“/SS", "광주/NNP", "의/JKG", "특징/NNG", "을/JKO", "잘/MAG", "보이/VV", "어/EC", "주/VX", "ㄹ/ETM", "수/NNB", "있/VA", "는/ETM", "‘/SS", "빛세/NNG", "권/XSN", "·/SP", "맛세/NNG", "권/XSN", "·/SP", "멋세/NNG", "권/XSN", "’/SS", "으로/JKB", "광주송정/NNP", "역세/NNG", "권/XSN", "을/JKO", "꾸미/VV", "어/EC", "보/VX", "기/ETN", "ㄹ/JKO", "제안/NNG", "하/XSV", "ㄴ다/EF", "”/SS", "고/JKQ", "강조/NNG", "하/XSV", "었/EP", "다/EF"], ["나아가/VV", "어/EC", "홍콩/NNP", "구룡역/NNP", ",/SP", "일본/NNP", "시나가와/NNP", ",/SP", "영국/NNP", "리버풀/NNP", ",/SP", "프랑스/NNP", "리옹/NNP", "등/NNB", "의/JKG", "역세/NNG", "권/XSN", "성공/NNG", "사례/NNG", "도/JX", "소개/NNG", "하/XSV", "었/EP", "다/EF"]]}, {"src": [["북구/NNP", ",/SP", "첨단/NNG", "과학/NNG", "산단/NNG", "인근/NNG", "4/SN", "천/NR", "840/SN", "㎡/SW", "규모/NNG", "…/SE", "5/SN", "월/NNB", "중/NNB", "개장/NNG"], ["북구/NNP", "는/JX", "“/SS", "북구/NNP", "첨단/NNG", "과학/NNG", "산업/NNG", "단지/NNG", "인근/NNG", "에/JKB", "4/SN", "차/NNB", "산업/NNG", "혁명/NNG", "의/JKG", "한/MM", "축/NNG", "이/VCP", "ㄴ/ETM", "드론/NNG", "산업/NNG", "육성/NNG", "기반/NNG", "마련/NNG", "과/JC", "드론/NNG", "레저/NNG", "문화/NNG", "확산/NNG", "을/JKO", "위하/VV", "어/EC", "‘/SS", "북구/NNP", "드론/NNG", "비행/NNG", "연습/NNG", "장/XSN", "’/SS", "을/JKO", "조성/NNG", "하/XSV", "고/EC", "시범/NNG", "운영/NNG", "에/JKB", "나서/VV", "었/EP", "다/EF", "”/SS", "고/JKQ", "13/SN", "일/NNB", "밝히/VV", "었/EP", "다/EF"], ["‘/SS", "드론/NNG", "비행/NNG", "연습/NNG", "장/XSN", "’/SS", "은/JX", "대촌동/NNP", "일원/NNG", "에/JKB", "4/SN", "천/NR", "840/SN", "㎡/SW", "규모/NNG", "로/JKB", "초보/NNG", "자/XSN", "구역/NNG", "1/SN", "천/NR", "000/SN", "㎡/SW", ",/SP", "레이싱/NNG", "및/MAJ", "산업/NNG", "테스트/NNG", "구역/NNG", "3/SN", "천/NR", "840/SN", "㎡/SW", "로/JKB", "조성/NNG", "하/XSV", "었/EP", "으며/EC", "시범/NNG", "운영/NNG", "기간/NNG", "동안/NNG", "운영/NNG", "상/XSN", "의/JKG", "문제/NNG", "점/NNG", "을/JKO", "파악/NNG", "하/XSV", "고/EC", "보완/NNG", "·/SP", "개선/NNG", "하/XSV", "어/EC", "5/SN", "월/NNB", "중/NNB", "정식/NNG", "으로/JKB", "개장/NNG", "하/XSV", "ㄹ/ETM", "예정/NNG", "이/VCP", "다/EF"], ["또한/MAG", ",/SP", "드론/NNG", "비행/NNG", "연습/NNG", "장/XSN", "운영/NNG", "이외/NNG", "에/JKB", "도/JX", "광주시/NNP", ",/SP", "유관/NNG", "기관/NNG", "과/JKB", "의/JKG", "협업/NNG", "을/JKO", "통하/VV", "ㄴ/ETM", "민간/NNG", "산업/NNG", "견인/NNG", "역할/NNG", "을/JKO", "하/VV", "ㄹ/ETM", "수/NNB", "있/VA", "는/ETM", "공공/NNG", "분야/NNG", "도입/NNG", "방안/NNG", "을/JKO", "구상/NNG", "중/NNB", "이/VCP", "며/EC", ",/SP", "교육/NNG", "기관/NNG", "과/JKB", "연계/NNG", "하/XSV", "ㄴ/ETM", "드론/NNG", "체험/NNG", "교실/NNG", "도/JX", "추진/NNG", "하/XSV", "ㄹ/ETM", "계획/NNG", "이/VCP", "다/EF"], ["특히/MAG", ",/SP", "드론/NNG", "시험/NNG", "비행/NNG", "을/JKO", "위하/VV", "어/EC", "비행/NNG", "제한/NNG", "구역/NNG", "밖/NNG", "에/JKB", "위치/NNG", "하/XSV", "ㄴ/ETM", "장소/NNG", "를/JKO", "찾/VV", "아/EC", "나서/VV", "아야/EC", "하/VX", "었/EP", "던/ETM", "광주/NNP", "지역/NNG", "드론/NNG", "동호/NNG", "회/XSN", ",/SP", "드론/NNG", "전문/NNG", "교육/NNG", "기관/NNG", ",/SP", "드론/NNG", "기업/NNG", "체/XSN", "등/NNB", "의/JKG", "불편/NNG", "을/JKO", "덜/VV", "게/EC", "되/VV", "ㄹ/ETM", "것/NNB", "으로/JKB", "보이/VV", "ㄴ다/EF"], ["드론/NNG", "비행/NNG", "연습/NNG", "장/XSN", "이용/NNG", "신청/NNG", "은/JX", "북구청/NNP", "민생/NNG", "경제/NNG", "과/NNG", "(/SS", "062/SN", "-/SS", "410/SN", "-/SS", "6112/SN", ")/SS", "로/JKB", "문의/NNG", "하/XSV", "면/EC", "되/VV", "고/EC", "시범/NNG", "운영/NNG", "기간/NNG", "중/NNB", "에/JKB", "는/JX", "5/SN", "인/NNG", "이상/NNG", "단체/NNG", ",/SP", "시제/NNG", "품/XSN", "테스트/NNG", "를/JKO", "위하/VV", "ㄴ/ETM", "드론/NNG", "기업/NNG", "위주/NNG", "로/JKB", "접수/NNG", "받/VV", "고/EC", "정식/NNG", "개장/NNG", "후/NNG", "에/JKB", "는/JX", "주민/NNG", "과/JC", "기업/NNG", "이/JKS", "별도/NNG", "의/JKG", "예약/NNG", "시스템/NNG", "을/JKO", "통하/VV", "어/EC", "이용/NNG", "이/JKS", "가능/NNG", "하/XSA", "다/EF"], ["문인/NNG", "북구/NNG", "청장/NNG", "은/JX", "“/SS", "드론/NNG", "산업/NNG", "은/JX", "4/SN", "차/NNB", "산업/NNG", "혁명/NNG", "의/JKG", "한/MM", "축/NNG", "으로서/JKB", "미래/NNG", "먹/NNG", "거리/NNB", "산업/NNG", "분야/NNG", "로/JKB", "확대/NNG", "하/XSV", "어/EC", "나가/VX", "어야/EC", "하/VX", "ㄹ/ETM", "것/NNB", "”/SS", "이/VCP", "라며/EC", "“/SS", "민선/NNG", "7/SN", "기/ETN", "시작/NNG", "부터/JX", "체계/NNG", "적/XSN", "이/VCP", "ㄴ/ETM", "준비/NNG", "를/JKO", "하/VV", "어/EC", "오/VX", "었/EP", "던/ETM", "만큼/NNB", "4/SN", "차/NNB", "산업/NNG", "융합/NNG", "미니/NNG", "클러스터/NNG", "사업/NNG", "과/JKB", "함께/MAG", "드론/NNG", "비행/NNG", "연습/NNG", "장/XSN", "이/JKS", "규제/NNG", "샌드박스/NNG", "역할/NNG", "을/JKO", "하/VV", "ㄹ/ETM", "수/NNB", "있/VA", "도록/EC", "매진/NNG", "하/XSV", "어/EC", "나가/VX", "겠/EP", "다/EF", "”/SS", "고/JKQ", "말/NNG", "하/XSV", "었/EP", "다/EF"], ["한편/NNG", ",/SP", "북구/NNP", "는/JX", "드론/NNG", "비행/NNG", "연습/NNG", "장/XSN", "에/JKB", "이용/NNG", "자/XSN", "의/JKG", "안전/NNG", "과/JC", "시설/NNG", "사용/NNG", "안내/NNG", "등/NNB", "을/JKO", "위하/VV", "어/EC", "드론/NNG", "전문/NNG", "자격/NNG", "증/XSN", "을/JKO", "소지/NNG", "하/XSV", "ㄴ/ETM", "전문/NNG", "요원/NNG", "을/JKO", "배치/NNG", "하/XSV", "ㄹ/ETM", "계획/NNG", "이/VCP", "다/EF"], ["최환준/NNP", "기자/NNG"]], "tgt": [["북구/NNP", "는/JX", "“/SS", "북구/NNP", "첨단/NNG", "과학/NNG", "산업/NNG", "단지/NNG", "인근/NNG", "에/JKB", "4/SN", "차/NNB", "산업/NNG", "혁명/NNG", "의/JKG", "한/MM", "축/NNG", "이/VCP", "ㄴ/ETM", "드론/NNG", "산업/NNG", "육성/NNG", "기반/NNG", "마련/NNG", "과/JC", "드론/NNG", "레저/NNG", "문화/NNG", "확산/NNG", "을/JKO", "위하/VV", "어/EC", "‘/SS", "북구/NNP", "드론/NNG", "비행/NNG", "연습/NNG", "장/XSN", "’/SS", "을/JKO", "조성/NNG", "하/XSV", "고/EC", "시범/NNG", "운영/NNG", "에/JKB", "나서/VV", "었/EP", "다/EF", "”/SS", "고/JKQ", "13/SN", "일/NNB", "밝히/VV", "었/EP", "다/EF"], ["‘/SS", "드론/NNG", "비행/NNG", "연습/NNG", "장/XSN", "’/SS", "은/JX", "대촌동/NNP", "일원/NNG", "에/JKB", "4/SN", "천/NR", "840/SN", "㎡/SW", "규모/NNG", "로/JKB", "초보/NNG", "자/XSN", "구역/NNG", "1/SN", "천/NR", "000/SN", "㎡/SW", ",/SP", "레이싱/NNG", "및/MAJ", "산업/NNG", "테스트/NNG", "구역/NNG", "3/SN", "천/NR", "840/SN", "㎡/SW", "로/JKB", "조성/NNG", "하/XSV", "었/EP", "으며/EC", "시범/NNG", "운영/NNG", "기간/NNG", "동안/NNG", "운영/NNG", "상/XSN", "의/JKG", "문제/NNG", "점/NNG", "을/JKO", "파악/NNG", "하/XSV", "고/EC", "보완/NNG", "·/SP", "개선/NNG", "하/XSV", "어/EC", "5/SN", "월/NNB", "중/NNB", "정식/NNG", "으로/JKB", "개장/NNG", "하/XSV", "ㄹ/ETM", "예정/NNG", "이/VCP", "다/EF"], ["한편/NNG", ",/SP", "북구/NNP", "는/JX", "드론/NNG", "비행/NNG", "연습/NNG", "장/XSN", "에/JKB", "이용/NNG", "자/XSN", "의/JKG", "안전/NNG", "과/JC", "시설/NNG", "사용/NNG", "안내/NNG", "등/NNB", "을/JKO", "위하/VV", "어/EC", "드론/NNG", "전문/NNG", "자격/NNG", "증/XSN", "을/JKO", "소지/NNG", "하/XSV", "ㄴ/ETM", "전문/NNG", "요원/NNG", "을/JKO", "배치/NNG", "하/XSV", "ㄹ/ETM", "계획/NNG", "이/VCP", "다/EF"]]}]