[{"src": [["이종근/NNP", "기자/NNG"], ["한국연극협회/NNP", "전북지회/NNP", ",/SP", "창작/NNG", "소/XPN", "극장/NNG", "과/JC", "공연/NNG", "예술소/NNG", "극장/NNG", "`/SW", "용/XSN", "'/SS", "서/JKB", "열리/VV", "어/EF"], ["배우/NNG", "의/JKG", "온전하/VA", "ㄴ/ETM", "숨/NNG", "소리/NNG", "느끼/VV", "어/EC", "지/VX", "는/ETM", "소/XPN", "극장/NNG", "연극/NNG", "제/XSN", "가/JKS", "전북/NNP", "에서/JKB", "열리/VV", "ㄴ다/EF"], ["특히/MAG", "배우/NNG", "의/JKG", "숨/NNG", "소리/NNG", "조차/JX", "온전하/VA", "게/EC", "느끼/VV", "ㄹ/ETM", "수/NNB", "있/VA", "는/ETM", "현장/NNG", "성/XSN", "의/JKG", "극대/NNG", "화/XSN", "를/JKO", "이루/VV", "어/EC", "오/VX", "ㄴ/ETM", "행사/NNG", "로/JKB", ",/SP", "연기/NNG", "자/XSN", "와/JC", "스태프/NNG", "능력/NNG", "배양/NNG", "등/NNB", "지역/NNG", "연극/NNG", "의/JKG", "발전/NNG", "을/JKO", "이루/VV", "게/EC", "하/VX", "ㄴ/ETM", "축제/NNG", "이/VCP", "기/ETN", "도/JX", "하/VX", "다/EF"]], "tgt": [["배우/NNG", "의/JKG", "온전하/VA", "ㄴ/ETM", "숨/NNG", "소리/NNG", "느끼/VV", "어/EC", "지/VX", "는/ETM", "소/XPN", "극장/NNG", "연극/NNG", "제/XSN", "가/JKS", "전북/NNP", "에서/JKB", "열리/VV", "ㄴ다/EF"], ["특히/MAG", "배우/NNG", "의/JKG", "숨/NNG", "소리/NNG", "조차/JX", "온전하/VA", "게/EC", "느끼/VV", "ㄹ/ETM", "수/NNB", "있/VA", "는/ETM", "현장/NNG", "성/XSN", "의/JKG", "극대/NNG", "화/XSN", "를/JKO", "이루/VV", "어/EC", "오/VX", "ㄴ/ETM", "행사/NNG", "로/JKB", ",/SP", "연기/NNG", "자/XSN", "와/JC", "스태프/NNG", "능력/NNG", "배양/NNG", "등/NNB", "지역/NNG", "연극/NNG", "의/JKG", "발전/NNG", "을/JKO", "이루/VV", "게/EC", "하/VX", "ㄴ/ETM", "축제/NNG", "이/VCP", "기/ETN", "도/JX", "하/VX", "다/EF"]]}, {"src": [["양정선/NNP", "기자/NNG"], ["고창/NNP", "무장현/NNP", "관아/NNG", "와/JC", "읍성/NNG", "출토/NNG", "비격/NNG", "진천뢰/NNP", "의/JKG", "보존/NNG", "과/JC", "활용/NNG", "을/JKO", "위하/VV", "ㄴ/ETM", "학술/NNG", "세미나/NNG", "가/JKS", "오/VV", "는/ETM", "15/SN", "일/NNB", "오후/NNG", "1/SN", "시/NNB", "에/JKB", "고창고인돌/NNG", "박물/NNG", "관/XSN", "에서/JKB", "열리/VV", "ㄴ다/EF"]], "tgt": [["고창/NNP", "무장현/NNP", "관아/NNG", "와/JC", "읍성/NNG", "출토/NNG", "비격/NNG", "진천뢰/NNP", "의/JKG", "보존/NNG", "과/JC", "활용/NNG", "을/JKO", "위하/VV", "ㄴ/ETM", "학술/NNG", "세미나/NNG", "가/JKS", "오/VV", "는/ETM", "15/SN", "일/NNB", "오후/NNG", "1/SN", "시/NNB", "에/JKB", "고창고인돌/NNG", "박물/NNG", "관/XSN", "에서/JKB", "열리/VV", "ㄴ다/EF"]]}, {"src": [["공현철/NNP", "기자/NNG"], ["오/VV", "는/ETM", "29/SN", "일/NNB", "~/SO", "30/SN", "일/NNB", "전동/NNG", "성당/NNG", "본당/NNG", "내부/NNG", "서/JKB", "‘/SS", "미디어/NNG", "아트/NNG", "쇼/NNG", "’/SS"], ["전동/NNG", "성당/NNG", "이/JKS", "건립/NNG", "130/SN", "주년/NNB", "을/JKO", "맞/VV", "어/EC", "본당/NNG", "내부/NNG", "를/JKO", "미디어/NNG", "아트/NNG", "쇼/NNG", "공간/NNG", "으로/JKB", "제공/NNG", "하/XSV", "기/ETN", "로/JKB", "하/VV", "었/EP", "다/EF"]], "tgt": []}, {"src": [["양정선/NNP", "기자/NNG"], ["오전/NNG", "8/SN", "시/NNB", "10/SN", "분/NNB", "입실/NNG", "마감/NNG", ",/SP", "착오/NNG", "시/NNG", "별도/NNG", "시험/NNG", "장/XSN", "응시/NNG", "가능/NNG"], ["■/SW", "오늘/NNG", "2020/SN", "대학/NNG", "수학/NNG", "능력/NNG", "시험/NNG"], ["수험/NNG", "생/XSN", "들/XSN", "의/JKG", "‘/SS", "결전/NNG", "의/JKG", "날/NNG", "’/SS", "이/JKS", "밝/VA", "었/EP", "다/EF"]], "tgt": []}, {"src": [["고/VV", "운영/NNG", "기자/NNG"], ["익산시/NNP", "가/JKS", "겨울/NNG", "철/NNG", "을/JKO", "맞/VV", "어/EC", "자연/NNG", "재난/NNG", "대비/NNG", "종합/NNG", "대책/NNG", "을/JKO", "추진/NNG", "하/XSV", "ㄹ/ETM", "TF/SL", "팀/NNG", "을/JKO", "구성/NNG", "하/XSV", "는/ETM", "등/NNB", "시민/NNG", "들/XSN", "의/JKG", "안전/NNG", "하/XSA", "ㄴ/ETM", "겨울/NNG", "나기/NNG", "정책/NNG", "을/JKO", "추진/NNG", "하/XSV", "ㄴ다/EF"]], "tgt": [["익산시/NNP", "가/JKS", "겨울/NNG", "철/NNG", "을/JKO", "맞/VV", "어/EC", "자연/NNG", "재난/NNG", "대비/NNG", "종합/NNG", "대책/NNG", "을/JKO", "추진/NNG", "하/XSV", "ㄹ/ETM", "TF/SL", "팀/NNG", "을/JKO", "구성/NNG", "하/XSV", "는/ETM", "등/NNB", "시민/NNG", "들/XSN", "의/JKG", "안전/NNG", "하/XSA", "ㄴ/ETM", "겨울/NNG", "나기/NNG", "정책/NNG", "을/JKO", "추진/NNG", "하/XSV", "ㄴ다/EF"]]}]