[{"src": [["계명대/NNP", "에서/JKB", "열리/VV", "ㄴ/ETM", "'/SS", "2019/SN", "실크로드/NNP", "인문/NNG", "학/XSN", "국제/NNG", "학술/NNG", "회의/NNG", "'/SS", "가/JKS", "참가/NNG", "자/XSN", "들/XSN", "이/JKS", "단체/NNG", "기념/NNG", "촬영/NNG", "을/JKO", "하/VV", "고/EC", "있/VX", "다/EF"], ["계명대/NNP", "(/SS", "총장/NNG", "신일희/NNP", ")/SS", "가/JKS", "지나/VV", "ㄴ/ETM", "18/SN", "일/NNB", "성서/NNG", "캠퍼스/NNG", "동천관/NNP", "국제/NNG", "세미나/NNG", "실/XSN", "에서/JKB", "'/SS", "2019/SN", "실크로드/NNP", "인문/NNG", "학/XSN", "국제/NNG", "학술/NNG", "회의/NNG", "'/SS", "를/JKO", "열/VV", "고/EC", "실크로드/NNP", "선상/NNG", "국가/NNG", "들/XSN", "의/JKG", "교류/NNG", "역사/NNG", "에/JKB", "대하/VV", "어/EC", "재/XPN", "조명/NNG", "하/VV", "는/ETM", "시간/NNG", "을/JKO", "가지/VV", "었/EP", "다/EF"], ["도로/NNG", "시/NNB", "웡/NNP", "미국/NNP", "버지니아대/NNP", "교수/NNG", ",/SP", "리차드/NNP", "폴츠/NNP", "캐나다/NNP", "콩코디아대/NNP", "교수/NNG", ",/SP", "조나단/NNP", "스카프/NNG", "미국/NNP", "펜실베니아/NNP", "쉬펜스버그대/NNP", "교수/NNG", "등/NNB", "국내/NNG", "외/NNB", "석학/NNG", "13/SN", "명/NNB", "이/JKS", "참가/NNG", "하/XSV", "어/EC", "'/SS", "둔황/NNG", "으로/JKB", "가/VV", "는/ETM", "길/NNG", ":/SP", "시공/NNG", "간적/MM", "매트릭스/NNG", "로서/JKB", "의/JKG", "실크/NNG", "로드/NNG", "'/SS", "를/JKO", "주제/NNG", "로/JKB", "발표/NNG", "와/JC", "토론/NNG", "의/JKG", "시간/NNG", "을/JKO", "가지/VV", "었/EP", "다/EF"], ["신일희/NNP", "계명대/NNP", "총장/NNG", "은/JX", "환영/NNG", "사/XSN", "를/JKO", "통하/VV", "어/EC", "\"/SS", "이번/NNG", "국제/NNG", "학술/NNG", "회의/NNG", "가/JKS", "서/NNG", "반구/NNG", "에서/JKB", "동/NNG", "반구/NNG", "를/JKO", "거치/VV", "어/EC", "이제/MAG", "다시/MAG", "중반구/NNG", "를/JKO", "향하/VV", "며/EC", "인류/NNG", "의/JKG", "미래/NNG", "에/JKB", "공존/NNG", "의/JKG", "가치/NNG", "를/JKO", "깨우/VV", "는/ETM", "기회/NNG", "가/JKC", "되/VV", "기/ETN", "ㄹ/JKO", "바라/VV", "ㄴ다/EF", "\"/SS", "고/JKQ", "말/NNG", "하/XSV", "었/EP", "다/EF"], ["김중순/NNP", "실크로드중앙아시아/NNP", "연구/NNG", "원/XSN", "장/XSN", "(/SS", "계명대/NNP", "한국/NNP", "문화/NNG", "정보/NNG", "학/XSN", "전공/NNG", "교수/NNG", ")/SS", "이/JKS", "'/SS", "중국/NNP", "의/JKG", "둔황/NNG", "과/JC", "인류/NNG", "문명/NNG", "사/XSN", "의/JKG", "둔황/NNG", "'/SS", "을/JKO", "주제/NNG", "로/JKB", "강연/NNG", "을/JKO", "가지/VV", "었/EP", "다/EF"], ["계명대/NNP", "의/JKG", "실크로드/NNP", "인문/NNG", "학/XSN", "국제/NNG", "학술/NNG", "회의/NNG", "는/JX", "경북도/NNP", "의/JKG", "전폭/NNG", "적/XSN", "이/VCP", "ㄴ/ETM", "지원/NNG", "과/JC", "협력/NNG", "으로/JKB", "개최/NNG", "되/XSV", "고/EC", "있/VX", "다/EF"]], "tgt": [["계명대/NNP", "(/SS", "총장/NNG", "신일희/NNP", ")/SS", "가/JKS", "지나/VV", "ㄴ/ETM", "18/SN", "일/NNB", "성서/NNG", "캠퍼스/NNG", "동천관/NNP", "국제/NNG", "세미나/NNG", "실/XSN", "에서/JKB", "'/SS", "2019/SN", "실크로드/NNP", "인문/NNG", "학/XSN", "국제/NNG", "학술/NNG", "회의/NNG", "'/SS", "를/JKO", "열/VV", "고/EC", "실크로드/NNP", "선상/NNG", "국가/NNG", "들/XSN", "의/JKG", "교류/NNG", "역사/NNG", "에/JKB", "대하/VV", "어/EC", "재/XPN", "조명/NNG", "하/VV", "는/ETM", "시간/NNG", "을/JKO", "가지/VV", "었/EP", "다/EF"], ["도로/NNG", "시/NNB", "웡/NNP", "미국/NNP", "버지니아대/NNP", "교수/NNG", ",/SP", "리차드/NNP", "폴츠/NNP", "캐나다/NNP", "콩코디아대/NNP", "교수/NNG", ",/SP", "조나단/NNP", "스카프/NNG", "미국/NNP", "펜실베니아/NNP", "쉬펜스버그대/NNP", "교수/NNG", "등/NNB", "국내/NNG", "외/NNB", "석학/NNG", "13/SN", "명/NNB", "이/JKS", "참가/NNG", "하/XSV", "어/EC", "'/SS", "둔황/NNG", "으로/JKB", "가/VV", "는/ETM", "길/NNG", ":/SP", "시공/NNG", "간적/MM", "매트릭스/NNG", "로서/JKB", "의/JKG", "실크/NNG", "로드/NNG", "'/SS", "를/JKO", "주제/NNG", "로/JKB", "발표/NNG", "와/JC", "토론/NNG", "의/JKG", "시간/NNG", "을/JKO", "가지/VV", "었/EP", "다/EF"], ["신일희/NNP", "계명대/NNP", "총장/NNG", "은/JX", "환영/NNG", "사/XSN", "를/JKO", "통하/VV", "어/EC", "\"/SS", "이번/NNG", "국제/NNG", "학술/NNG", "회의/NNG", "가/JKS", "서/NNG", "반구/NNG", "에서/JKB", "동/NNG", "반구/NNG", "를/JKO", "거치/VV", "어/EC", "이제/MAG", "다시/MAG", "중반구/NNG", "를/JKO", "향하/VV", "며/EC", "인류/NNG", "의/JKG", "미래/NNG", "에/JKB", "공존/NNG", "의/JKG", "가치/NNG", "를/JKO", "깨우/VV", "는/ETM", "기회/NNG", "가/JKC", "되/VV", "기/ETN", "ㄹ/JKO", "바라/VV", "ㄴ다/EF", "\"/SS", "고/JKQ", "말/NNG", "하/XSV", "었/EP", "다/EF"]]}, {"src": [["3/SN", "당/NNG", "원내/NNG", "대표/NNG", "회동/NNG", "성과/NNG", "없이/MAG", "끝나/VV", "어/EF"], ["민주/NNP", "“/SS", "실무/NNG", "협상/NNG", "지켜보/VV", "ㄹ/ETM", "것/NNB", "”/SS", "신중/NNG"], ["한국/NNP", "“/SS", "죄덮/NNG", "는/JX", "은폐처/NNG", "”/SS", "설치/NNG", "불가/NNG"], ["합의/NNG", "불발/NNG", "때/NNG", "여야/NNG", "4/SN", "당/NNG", "공조/NNG", "재/XPN", "추진/NNG"], ["여야/NNG", "3/SN", "당/NNG", "교섭/NNG", "단체/NNG", "원내/NNG", "대표/NNG", "들/XSN", "은/JX", "21/SN", "일/NNB", "국회/NNG", "에서/JKB", "만나/VV", "어/EC", "검찰/NNG", "개혁/NNG", "의/JKG", "핵심/NNG", "쟁점/NNG", "이/VCP", "ㄴ/ETM", "고위/NNG", "공직/NNG", "자/XSN", "범죄/NNG", "수사/NNG", "처/XSN", "(/SS", "공수처/NNG", ")/SS", "신설/NNG", "법안/NNG", "처리/NNG", "방안/NNG", "을/JKO", "논의/NNG", "하/XSV", "었/EP", "으나/EC", "입장/NNG", "차/NNG", "를/JKO", "좁히/VV", "지/EC", "못하/VX", "었/EP", "다/EF"], ["더불어민주당/NNP", "이인영/NNP", "원내/NNG", "대표/NNG", "는/JX", "이날/NNG", "한국당/NNP", "나경원/NNP", "·/SP", "바른미래당/NNP", "오신환/NNP", "원내/NNG", "대표/NNG", "와/JC", "회동/NNG", "직후/NNG", "기자/NNG", "들/XSN", "과/JKB", "만나/VV", "어/EC", "“/SS", "검찰/NNG", "개혁/NNG", "과/JC", "공수처법/NNG", "에/JKB", "대하/VV", "어/EC", "이런저런/MM", "얘기/NNG", "를/JKO", "하/VV", "었/EP", "지만/EC", "쟁점/NNG", "이/JKS", "분명히/MAG", "있/VA", "는/ETM", "것/NNB", "이/VCP", "라/EC", "그/MM", "쟁점/NNG", "은/JX", "해소/NNG", "되/XSV", "지/EC", "않/VX", "었/EP", "다/EF", "”/SS", "면서/EC", "“/SS", "공수/NNG", "처/XSN", "는/JX", "이견/NNG", "이/JKS", "명확하/VA", "ㄴ/ETM", "부분/NNG", "이/VCP", "라/EC", ",/SP", "수/NNG", "요일/NNG", "(/SS", "23/SN", "일/NNB", ")/SS", "에/JKB", "실무/NNG", "협상/NNG", "과정/NNG", "을/JKO", "지켜보/VV", "고/EC", "재/XPN", "논의/NNG", "하/XSV", "ㄴ다/EF", "”/SS", "고/JKQ", "설명/NNG", "하/XSV", "었/EP", "다/EF"], ["이/MM", "원내/NNG", "대표/NNG", "는/JX", "23/SN", "일/NNB", "실무/NNG", "협상/NNG", "에서/JKB", "도/JX", "공수/NNG", "처/XSN", "에/JKB", "대하/VV", "어/EC", "한국당/NNP", "과/JKB", "합의/NNG", "가/JKS", "안/MAG", "되/XSV", "ㄹ/ETM", "경우/NNG", "대안/NNG", "을/JKO", "묻/VV", "는/ETM", "질문/NNG", "에/JKB", "“/SS", "아직/MAG", "거기/NP", "까지/JX", "가/VV", "지/EC", "말/VX", "어/EC", "달/VX", "라/EF", "”/SS", "면서/EC", "“/SS", "오늘/MAG", "여기/NP", "서/JKB", "그/MM", "얘기/NNG", "는/JX", "하/VV", "ㄹ/ETM", "수/NNB", "있/VA", "는/ETM", "성격/NNG", "이/JKC", "아니/VCN", "다/EF", "”/SS", "라고/JKQ", "신중/NNG", "론/XSN", "을/JKO", "펴/VV", "었/EP", "다/EF"], ["하지만/MAJ", "한국당/NNP", "나경원/NNP", "원내/NNG", "대표/NNG", "는/JX", "앞서/MAG", "열리/VV", "ㄴ/ETM", "최고/NNG", "위원/NNG", "회의/NNG", "에서/JKB", "“/SS", "여당/NNG", "이/JKS", "공수/NNG", "처/XSN", "법안/NNG", "을/JKO", "우선/NNG", "적/XSN", "으로/JKB", "처리/NNG", "하/XSV", "겠/EP", "다고/EC", "하/VV", "ㄴ다/EF", "”/SS", "면서/EC", "“/SS", "있/VA", "는/ETM", "죄/NNG", "덮/VV", "는/ETM", "‘/SS", "은폐처/NNG", "’/SS", ",/SP", "없/VA", "는/ETM", "죄/NNG", "만들/VV", "는/ETM", "‘/SS", "공포처/NNG", "’/SS", "를/JKO", "만들/VV", "겠/EP", "다는/ETM", "것/NNB", "”/SS", "이라고/JKQ", "공수/NNG", "처/XSN", "반대/NNG", "입장/NNG", "을/JKO", "재/XPN", "확인/NNG", "하/XSV", "어/EC", "추가/NNG", "협상/NNG", "에/JKB", "도/JX", "합의/NNG", "가능/NNG", "성/XSN", "은/JX", "거의/MAG", "없/VA", "다는/ETM", "것/NNB", "이/JKS", "중론/NNG", "이/VCP", "다/EF"], ["때문/NNB", "에/JKB", "정치/NNG", "권/XSN", "에서/JKB", "‘/SS", "공수처법/NNG", "先/SH", "처리/NNG", "’/SS", "를/JKO", "벼르/VV", "고/EC", "있/VX", "는/ETM", "민주당/NNP", "으로서/JKB", "ㄴ/JX", "한국당/NNP", "을/JKO", "제외/NNG", "하/XSV", "ㄴ/ETM", "여야/NNG", "4/SN", "당/NNG", "의/JKG", "‘/SS", "패스트/NNG", "트랙/NNG", "(/SS", "신속/NNG", "처리/NNG", "안건/NNG", "지정/NNG", ")/SS", "공조/NNG", "’/SS", "복원/NNG", "여부/NNG", "에/JKB", "법안/NNG", "처리/NNG", "의/JKG", "성패/NNG", "가/JKS", "달리/VV", "어/EC", "있/VX", "다는/ETM", "분석/NNG", "이/VCP", "다/EF"], ["이/NP", "와/JKB", "관련/NNG", ",/SP", "대안/NNG", "정치/NNG", "(/SS", "가칭/NNG", ")/SS", "유성엽/NNP", "대표/NNG", "는/JX", "이날/NNG", "의원/NNG", "-/SS", "창당/NNG", "준비/NNG", "기획/NNG", "단/XSN", "연석/NNG", "회의/NNG", "후/NNG", "기자/NNG", "들/XSN", "과/JKB", "만나/VV", "어/EC", "“/SS", "조국/NNG", "장관/NNG", "사퇴/NNG", "이후/NNG", "(/SS", "여권/NNG", ")/SS", "내부/NNG", "에서/JKB", "사과/NNG", "나/JX", "책임지/VV", "는/ETM", "모습/NNG", "은/JX", "보이/VV", "지/EC", "않/VX", "고/EC", "검찰/NNG", "개혁/NNG", ",/SP", "또/MAG", "공수/NNG", "처/XSN", "설치/NNG", "법/XSN", "만/JX", "떼/VV", "어/EC", "내/VX", "어/EC", "처리/NNG", "하/XSV", "겠/EP", "다고/EC", "하/VV", "ㄴ다/EF", "”/SS", "면서/EC", "“/SS", "아주/MAG", "오만/NNG", "하/XSA", "ㄴ/ETM", "발상/NNG", "이/VCP", "다/EF"], ["또한/MAG", "바른미래당/NNP", "내/NNB", "비/XPN", "당권/NNG", "파/XSN", "모임/NNG", "이/VCP", "ㄴ/ETM", "‘/SS", "변화/NNG", "와/JC", "혁신/NNG", "을/JKO", "위하/VV", "ㄴ/ETM", "비상/NNG", "행동/NNG", "(/SS", "변혁/NNG", ")/SS", "’/SS", "을/JKO", "이끌/VV", "는/ETM", "유승민/NNP", "의원/NNG", "(/SS", "대구/NNP", "동구을/NNP", ")/SS", "은/JX", "한/MM", "언론/NNG", "인터뷰/NNG", "에서/JKB", "“/SS", "여권/NNG", "이/JKS", "추진/NNG", "하/XSV", "는/ETM", "선거/NNG", "법/NNG", "개정/NNG", "안/NNG", "과/JC", "공수/NNG", "처/XSN", "법안/NNG", "에/JKB", "반대/NNG", "하/XSV", "며/EC", "12/SN", "월/NNB", "초/NNB", "정기/NNG", "국회/NNG", "마지막/NNG", "본/NNG", "회의/NNG", "까지/JX", "이/MM", "법안/NNG", "을/JKO", "막/VV", "어/EC", "내/VX", "는/ETM", "소명/NNG", "을/JKO", "다/MAG", "하/XSV", "겠/EP", "다/EF", "”/SS", "고/JKQ", "밝히/VV", "었/EP", "다/EF"], ["현재/MAG", "의석/NNG", "분포/NNG", "를/JKO", "보/VV", "면/EC", "민주당/NNP", "128/SN", "석/NNB", ",/SP", "한국당/NNP", "110/SN", "석/NNB", ",/SP", "바른미래당/NNP", "28/SN", "석/NNB", ",/SP", "정의당/NNP", "6/SN", "석/NNB", ",/SP", "민평/NNP", "당/XSN", "4/SN", "석/NNB", ",/SP", "우리/NP", "공화당/NNP", "2/SN", "석/NNB", ",/SP", "민중/NNG", "당/XSN", "1/SN", "석/NNB", ",/SP", "무/XPN", "소속/NNG", "18/SN", "석/NNB", "중/NNB", "대안/NNG", "정치/NNG", "9/SN", "석/NNB", ",/SP", "나머지/NNG", "9/SN", "석/NNB", "(/SS", "친/SH", "여/XSN", "5/SN", "석/NNB", ",/SP", "친야/NNG", "4/SN", "석/NNB", ")/SS", "등/NNB", "이/VCP", "다/EF"], ["권혁식/NNP", "기자/NNG", "kwonhs/SL", "@/SW", "yeongnamcom/SL"]], "tgt": [["여야/NNG", "3/SN", "당/NNG", "교섭/NNG", "단체/NNG", "원내/NNG", "대표/NNG", "들/XSN", "은/JX", "21/SN", "일/NNB", "국회/NNG", "에서/JKB", "만나/VV", "어/EC", "검찰/NNG", "개혁/NNG", "의/JKG", "핵심/NNG", "쟁점/NNG", "이/VCP", "ㄴ/ETM", "고위/NNG", "공직/NNG", "자/XSN", "범죄/NNG", "수사/NNG", "처/XSN", "(/SS", "공수처/NNG", ")/SS", "신설/NNG", "법안/NNG", "처리/NNG", "방안/NNG", "을/JKO", "논의/NNG", "하/XSV", "었/EP", "으나/EC", "입장/NNG", "차/NNG", "를/JKO", "좁히/VV", "지/EC", "못하/VX", "었/EP", "다/EF"], ["더불어민주당/NNP", "이인영/NNP", "원내/NNG", "대표/NNG", "는/JX", "이날/NNG", "한국당/NNP", "나경원/NNP", "·/SP", "바른미래당/NNP", "오신환/NNP", "원내/NNG", "대표/NNG", "와/JC", "회동/NNG", "직후/NNG", "기자/NNG", "들/XSN", "과/JKB", "만나/VV", "어/EC", "“/SS", "검찰/NNG", "개혁/NNG", "과/JC", "공수처법/NNG", "에/JKB", "대하/VV", "어/EC", "이런저런/MM", "얘기/NNG", "를/JKO", "하/VV", "었/EP", "지만/EC", "쟁점/NNG", "이/JKS", "분명히/MAG", "있/VA", "는/ETM", "것/NNB", "이/VCP", "라/EC", "그/MM", "쟁점/NNG", "은/JX", "해소/NNG", "되/XSV", "지/EC", "않/VX", "었/EP", "다/EF", "”/SS", "면서/EC", "“/SS", "공수/NNG", "처/XSN", "는/JX", "이견/NNG", "이/JKS", "명확하/VA", "ㄴ/ETM", "부분/NNG", "이/VCP", "라/EC", ",/SP", "수/NNG", "요일/NNG", "(/SS", "23/SN", "일/NNB", ")/SS", "에/JKB", "실무/NNG", "협상/NNG", "과정/NNG", "을/JKO", "지켜보/VV", "고/EC", "재/XPN", "논의/NNG", "하/XSV", "ㄴ다/EF", "”/SS", "고/JKQ", "설명/NNG", "하/XSV", "었/EP", "다/EF"], ["이/MM", "원내/NNG", "대표/NNG", "는/JX", "23/SN", "일/NNB", "실무/NNG", "협상/NNG", "에서/JKB", "도/JX", "공수/NNG", "처/XSN", "에/JKB", "대하/VV", "어/EC", "한국당/NNP", "과/JKB", "합의/NNG", "가/JKS", "안/MAG", "되/XSV", "ㄹ/ETM", "경우/NNG", "대안/NNG", "을/JKO", "묻/VV", "는/ETM", "질문/NNG", "에/JKB", "“/SS", "아직/MAG", "거기/NP", "까지/JX", "가/VV", "지/EC", "말/VX", "어/EC", "달/VX", "라/EF", "”/SS", "면서/EC", "“/SS", "오늘/MAG", "여기/NP", "서/JKB", "그/MM", "얘기/NNG", "는/JX", "하/VV", "ㄹ/ETM", "수/NNB", "있/VA", "는/ETM", "성격/NNG", "이/JKC", "아니/VCN", "다/EF", "”/SS", "라고/JKQ", "신중/NNG", "론/XSN", "을/JKO", "펴/VV", "었/EP", "다/EF"]]}, {"src": [["리얼미터/NNP", "YTN/SL", "전국/NNG", "성인/NNG", "대상/NNG", "조사/NNG"], ["고위/NNG", "공직/NNG", "자/XSN", "범죄/NNG", "수사/NNG", "처/XSN", "(/SS", "공수처/NNG", ")/SS", "설치/NNG", "를/JKO", "찬성/NNG", "하/XSV", "는/ETM", "국민/NNG", "이/JKS", "반대/NNG", "하/XSV", "는/ETM", "국민/NNG", "보다/JKB", "많/VA", "다는/ETM", "여론/NNG", "조사/NNG", "결과/NNG", "가/JKS", "21/SN", "일/NNB", "나오/VV", "었/EP", "다/EF"], ["리얼미터/NNP", "가/JKS", "YTN/SL", "의/JKG", "의뢰/NNG", "로/JKB", "지나/VV", "ㄴ/ETM", "18/SN", "일/NNB", "전국/NNG", "19/SN", "세/NNB", "이상/NNG", "성인/NNG", "501/SN", "명/NNB", "을/JKO", "대상/NNG", "으로/JKB", "조사/NNG", "하/XSV", "ㄴ/ETM", "결과/NNG", ",/SP", "찬성/NNG", "응답/NNG", "은/JX", "514/SN", "%/SW", "(/SS", "매우/MAG", "찬성/NNG", "386/SN", "%/SW", ",/SP", "찬성/NNG", "하/XSV", "는/ETM", "편/NNB", "128/SN", "%/SW", ")/SS", ",/SP", "반대/NNG", "응답/NNG", "은/JX", "412/SN", "%/SW", "(/SS", "매우/MAG", "반대/NNG", "266/SN", "%/SW", ",/SP", "반대/NNG", "하/XSV", "는/ETM", "편/NNB", "146/SN", "%/SW", ")/SS", "로/JKB", "집계/NNG", "되/XSV", "었/EP", "다/EF"], ["지나/VV", "ㄴ/ETM", "3/SN", "월/NNB", "리얼미터/NNP", "가/JKS", "오마이뉴스/NNP", "의뢰/NNG", "로/JKB", "공수/NNG", "처/XSN", "설치/NNG", "에/JKB", "대하/VV", "ㄴ/ETM", "여론/NNG", "조사/NNG", "를/JKO", "하/VV", "었/EP", "을/ETM", "때/NNG", "와/JKB", "비교/NNG", "하/XSV", "면/EC", "찬성/NNG", "은/JX", "줄/VV", "고/EC", "반대/NNG", "가/JKS", "늘어나/VV", "ㄴ/ETM", "것/NNB", "이/VCP", "다/EF"], ["3/SN", "월/NNB", "조사/NNG", "에서/JKB", "ㄴ/JX", "찬성/NNG", "응답/NNG", "이/JKS", "652/SN", "%/SW", "이/VCP", "었/EP", "고/EC", ",/SP", "반대/NNG", "응답/NNG", "이/JKS", "174/SN", "%/SW", "이/VCP", "었/EP", "다/EF"], ["이번/NNG", "조사/NNG", "결과/NNG", "를/JKO", "지역/NNG", "별/XSN", "로/JKB", "분석/NNG", "하/XSV", "면/EC", ",/SP", "찬성/NNG", "응답/NNG", "은/JX", "광주/NNP", "·/SP", "전라/NNP", "(/SS", "찬성/NNG", "707/SN", "%/SW", "vs/SL", "반대/NNG", "224/SN", "%/SW", ")/SS", ",/SP", "경기/NNP", "·/SP", "인천/NNP", "(/SS", "552/SN", "%/SW", "vs/SL", "381/SN", "%/SW", ")/SS", ",/SP", "서울/NNP", "(/SS", "540/SN", "%/SW", "vs/SL", "390/SN", "%/SW", ")/SS", ",/SP", "대구/NNP", "·/SP", "경북/NNP", "(/SS", "540/SN", "%/SW", "vs/SL", "413/SN", "%/SW", ")/SS", "순/NNB", "으로/JKB", "많/VA", "었/EP", "다/EF"], ["여성/NNG", "(/SS", "534/SN", "%/SW", "vs/SL", "368/SN", "%/SW", ")/SS", "이/JKS", "남성/NNG", "(/SS", "494/SN", "%/SW", "vs/SL", "457/SN", "%/SW", ")/SS", "보다/JKB", "찬성/NNG", "률/XSN", "이/JKS", "높/VA", "었/EP", "고/EC", ",/SP", "이념/NNG", "성향/NNG", "별/XSN", "로/JKB", "는/JX", "진보/NNG", "층/XSN", "(/SS", "818/SN", "%/SW", "vs/SL", "137/SN", "%/SW", ")/SS", ",/SP", "지지/NNG", "정당/NNG", "별/XSN", "로/JKB", "는/JX", "더불어민주당/NNP", "지지/NNG", "층/XSN", "(/SS", "935/SN", "%/SW", "vs/SL", "36/SN", "%/SW", ")/SS", "에서/JKB", "찬성/NNG", "응답/NNG", "이/JKS", "반대/NNG", "응답/NNG", "을/JKO", "웃돌/VV", "었/EP", "다/EF"], ["김상현/NNP", "기자/NNG", "shkim/SL", "@/SW", "yeongnamcom/SL"]], "tgt": [["고위/NNG", "공직/NNG", "자/XSN", "범죄/NNG", "수사/NNG", "처/XSN", "(/SS", "공수처/NNG", ")/SS", "설치/NNG", "를/JKO", "찬성/NNG", "하/XSV", "는/ETM", "국민/NNG", "이/JKS", "반대/NNG", "하/XSV", "는/ETM", "국민/NNG", "보다/JKB", "많/VA", "다는/ETM", "여론/NNG", "조사/NNG", "결과/NNG", "가/JKS", "21/SN", "일/NNB", "나오/VV", "었/EP", "다/EF"], ["리얼미터/NNP", "가/JKS", "YTN/SL", "의/JKG", "의뢰/NNG", "로/JKB", "지나/VV", "ㄴ/ETM", "18/SN", "일/NNB", "전국/NNG", "19/SN", "세/NNB", "이상/NNG", "성인/NNG", "501/SN", "명/NNB", "을/JKO", "대상/NNG", "으로/JKB", "조사/NNG", "하/XSV", "ㄴ/ETM", "결과/NNG", ",/SP", "찬성/NNG", "응답/NNG", "은/JX", "514/SN", "%/SW", "(/SS", "매우/MAG", "찬성/NNG", "386/SN", "%/SW", ",/SP", "찬성/NNG", "하/XSV", "는/ETM", "편/NNB", "128/SN", "%/SW", ")/SS", ",/SP", "반대/NNG", "응답/NNG", "은/JX", "412/SN", "%/SW", "(/SS", "매우/MAG", "반대/NNG", "266/SN", "%/SW", ",/SP", "반대/NNG", "하/XSV", "는/ETM", "편/NNB", "146/SN", "%/SW", ")/SS", "로/JKB", "집계/NNG", "되/XSV", "었/EP", "다/EF"]]}, {"src": [["■/SW", "정경심/NNP", "영장/NNG", "청구/NNG", "엇갈리/VV", "ㄴ/ETM", "반응/NNG"], ["검찰/NNG", "이/JKS", "21/SN", "일/NNB", "조국/NNP", "전/MM", "법무/NNG", "부/XSN", "장관/NNG", "의/JKG", "부인/NNG", "정경심/NNP", "동양대/NNP", "교수/NNG", "에/JKB", "대하/VV", "어/EC", "구속/NNG", "영장/NNG", "을/JKO", "청구/NNG", "하/XSV", "자/EC", ",/SP", "야당/NNG", "은/JX", "환영/NNG", "을/JKO", "표/NNG", "하/XSV", "며/EC", "엄정하/VA", "ㄴ/ETM", "수사/NNG", "를/JKO", "촉구/NNG", "하/XSV", "었/EP", "다/EF"], ["자유한국당/NNP", "황교안/NNP", "대표/NNG", "는/JX", "이날/NNG", "국회/NNG", "에서/JKB", "열리/VV", "ㄴ/ETM", "당/NNG", "최고/NNG", "위원/NNG", "회의/NNG", "를/JKO", "마치/VV", "ㄴ/ETM", "뒤/NNG", "“/SS", "국민/NNG", "들/XSN", "도/JX", "그렇/VA", "게/EC", "생각/NNG", "하/XSV", "ㄹ/ETM", "것/NNB", "”/SS", "이/VCP", "라며/EC", "“/SS", "검찰/NNG", "에서/JKB", "국민/NNG", "의/JKG", "뜻/NNG", "을/JKO", "받들/VV", "어/EC", "구속/NNG", "영장/NNG", "을/JKO", "청구/NNG", "하/XSV", "ㄴ/ETM", "것/NNB", "이/VCP", "라고/EC", "생각/NNG", "하/XSV", "ㄴ다/EF", "”/SS", "고/JKQ", "밝히/VV", "었/EP", "다/EF"], ["이어/MAG", "“/SS", "당연히/MAG", "구속/NNG", "되/XSV", "어야/EC", "하/VX", "는/ETM", "사안/NNG", "”/SS", "이/VCP", "라며/EC", "“/SS", "법원/NNG", "이/JKS", "또/MAG", "정권/NNG", "눈/NNG", "치/NNG", "를/JKO", "보/VV", "고/EC", "영장/NNG", "을/JKO", "기각/NNG", "하/XSV", "는/ETM", "일/NNG", "이/JKS", "없/VA", "기/ETN", "를/JKO", "바라/VV", "ㄴ다/EF"], ["바른미래당/NNP", "도/JX", "조/NNP", "전/MM", "장관/NNG", "동생/NNG", "에/JKB", "대하/VV", "ㄴ/ETM", "영각/NNG", "기각/NNG", "사례/NNG", "를/JKO", "반복/NNG", "하/XSV", "어서/EC", "는/JX", "안/MAG", "되/VV", "ㄴ다며/EC", "맞/XPN", "장구/NNG", "를/JKO", "치/VV", "었/EP", "다/EF"], ["김정화/NNP", "바른미래당/NNP", "대변/NNG", "인/XSN", "은/JX", "브리핑/NNG", "을/JKO", "통하/VV", "어/EC", "“/SS", "혐의/NNG", "의/JKG", "무겁/VA", "ㅁ/ETN", ",/SP", "충분하/VA", "ㄴ/ETM", "정황/NNG", "과/JC", "증거/NNG", ",/SP", "증거/NNG", "인멸/NNG", "을/JKO", "시도/NNG", "하/XSV", "ㄴ/ETM", "경험/NNG", "으로/JKB", "미루/VV", "어/EC", "보/VX", "ㄹ/ETM", "때/NNG", ",/SP", "구속/NNG", "영장/NNG", "청구/NNG", "는/JX", "너무나/MAG", "당연하/VA", "ㄴ/ETM", "조치/NNG", "”/SS", "이/VCP", "라며/EC", "“/SS", "꽝/NNG", "이/JKS", "없/VA", "는/ETM", "주사위/NNG", "처럼/JKB", "정경심/NNP", "씨/NNB", "에/JKB", "대하/VV", "ㄴ/ETM", "구속/NNG", "은/JX", "불가피하/VA", "ㄴ/ETM", "상황/NNG", "이/VCP", "다/EF"], ["반면/NNG", ",/SP", "민주당/NNP", "은/JX", "당/NNG", "차원/NNG", "의/JKG", "입장/NNG", "을/JKO", "내/VV", "지/EC", "않/VX", "었/EP", "다/EF"], ["민주당/NNP", "이/JKS", "정/NNP", "교수/NNG", "영장/NNG", "청구/NNG", "에/JKB", "대하/VV", "어/EC", "공식/NNG", "입장/NNG", "을/JKO", "내/VV", "지/EC", "않/VX", "는/ETM", "것/NNB", "은/JX", "자칫/MAG", "‘/SS", "사법/NNG", "부/NNG", "압박/NNG", "’/SS", "이/VCP", "라는/ETM", "오해/NNG", "를/JKO", "불러일으키/VV", "ㄹ/ETM", "수/NNB", "있/VA", "다는/ETM", "판단/NNG", "에/JKB", "따르/VV", "ㄴ/ETM", "것/NNB", "으로/JKB", "보이/VV", "ㄴ다/EF"], ["김상현/NNP", "기자/NNG", "shkim/SL", "@/SW", "yeongnamcom/SL"], ["정재훈/NNP", "기자/NNG", "jjhoon/SL", "@/SW", "yeongnamcom/SL"]], "tgt": [["검찰/NNG", "이/JKS", "21/SN", "일/NNB", "조국/NNP", "전/MM", "법무/NNG", "부/XSN", "장관/NNG", "의/JKG", "부인/NNG", "정경심/NNP", "동양대/NNP", "교수/NNG", "에/JKB", "대하/VV", "어/EC", "구속/NNG", "영장/NNG", "을/JKO", "청구/NNG", "하/XSV", "자/EC", ",/SP", "야당/NNG", "은/JX", "환영/NNG", "을/JKO", "표/NNG", "하/XSV", "며/EC", "엄정하/VA", "ㄴ/ETM", "수사/NNG", "를/JKO", "촉구/NNG", "하/XSV", "었/EP", "다/EF"], ["자유한국당/NNP", "황교안/NNP", "대표/NNG", "는/JX", "이날/NNG", "국회/NNG", "에서/JKB", "열리/VV", "ㄴ/ETM", "당/NNG", "최고/NNG", "위원/NNG", "회의/NNG", "를/JKO", "마치/VV", "ㄴ/ETM", "뒤/NNG", "“/SS", "국민/NNG", "들/XSN", "도/JX", "그렇/VA", "게/EC", "생각/NNG", "하/XSV", "ㄹ/ETM", "것/NNB", "”/SS", "이/VCP", "라며/EC", "“/SS", "검찰/NNG", "에서/JKB", "국민/NNG", "의/JKG", "뜻/NNG", "을/JKO", "받들/VV", "어/EC", "구속/NNG", "영장/NNG", "을/JKO", "청구/NNG", "하/XSV", "ㄴ/ETM", "것/NNB", "이/VCP", "라고/EC", "생각/NNG", "하/XSV", "ㄴ다/EF", "”/SS", "고/JKQ", "밝히/VV", "었/EP", "다/EF"], ["이어/MAG", "“/SS", "당연히/MAG", "구속/NNG", "되/XSV", "어야/EC", "하/VX", "는/ETM", "사안/NNG", "”/SS", "이/VCP", "라며/EC", "“/SS", "법원/NNG", "이/JKS", "또/MAG", "정권/NNG", "눈/NNG", "치/NNG", "를/JKO", "보/VV", "고/EC", "영장/NNG", "을/JKO", "기각/NNG", "하/XSV", "는/ETM", "일/NNG", "이/JKS", "없/VA", "기/ETN", "를/JKO", "바라/VV", "ㄴ다/EF"]]}, {"src": [["산학/NNG", "연관/NNG", "14/SN", "개/NNB", "기관/NNG", "협의/NNG", "체/XSN", "출범/NNG"], ["전문/NNG", "인력/NNG", "300/SN", "여/XSN", "명/NNB", "사업/NNG", "별/XSN", "지원/NNG", "단/XSN"], ["신약/NNG", "등/NNB", "바이오/NNG", "사업/NNG", "발굴/NNG", "∼/SO", "사업/NNG", "화/XSN"], ["경북도/NNP", "가/JKS", "산/NNG", "·/SP", "학/NNG", "·/SP", "연/NNG", "·/SP", "관/NNG", "이/JKS", "참여/NNG", "하/XSV", "는/ETM", "거버넌스/NNG", "조직/NNG", "을/JKO", "구성/NNG", "하/XSV", "어/EC", "5/SN", "차/NNB", "산업/NNG", "의/JKG", "핵심/NNG", "이/VCP", "ㄴ/ETM", "바이오/NNG", "생명/NNG", "산업/NNG", "육성/NNG", "에/JKB", "본격/NNG", "나서/VV", "ㄴ다/EF"], ["협의/NNG", "체/XSN", "는/JX", "기관/NNG", "별/XSN", "업무/NNG", "특성/NNG", "과/JC", "전문/NNG", "성/XSN", "에/JKB", "따르/VV", "어/EC", "△/SW", "백신/NNG", "·/SP", "신약/NNG", "△/SW", "식품/NNG", "·/SP", "생명/NNG", "기술/NNG", "△/SW", "한방/NNG", "·/SP", "테라피/NNP", "·/SP", "웰빙/NNG", "등/NNB", "3/SN", "개/NNB", "분야/NNG", "로/JKB", "운영/NNG", "되/XSV", "ㄴ다/EF"], ["특히/MAG", "협의/NNG", "체/XSN", "에/JKB", "소속/NNG", "되/XSV", "ㄴ/ETM", "연구/NNG", "기관/NNG", "·/SP", "대학/NNG", "·/SP", "기업/NNG", "의/JKG", "R/SL", "&/SW", "D/SL", "장비/NNG", "의/JKG", "공동/NNG", "활용/NNG", "을/JKO", "위하/VV", "ㄴ/ETM", "통합/NNG", "시스템/NNG", "구축/NNG", "도/JX", "추진/NNG", "하/XSV", "ㄴ다/EF"], ["도/NNG", "가/JKS", "생명/NNG", "산업/NNG", "에/JKB", "적극/NNG", "적/XSN", "이/VCP", "ㄴ/ETM", "것/NNB", "은/JX", "선진/NNG", "국/XSN", "이/JKS", "이미/MAG", "생명/NNG", "의학/NNG", "(/SS", "줄기/NNG", "세포/NNG", ")/SS", "·/SP", "바이오/NNG", "에너지/NNG", ",/SP", "비/XPN", "식품/NNG", "바이오/NNG", "기술/NNG", ",/SP", "재생/NNG", "의료/NNG", "등/NNB", "‘/SS", "바이오/NNG", "경제/NNG", "시대/NNG", "’/SS", "를/JKO", "준비/NNG", "하/XSV", "고/EC", "있/VX", "기/ETN", "때문/NNB", "이/VCP", "다/EF"], ["이철우/NNP", "도/NNG", "지사/NNG", "는/JX", "“/SS", "생명/NNG", "산업/NNG", "발전/NNG", "을/JKO", "위하/VV", "어/EC", "거버넌스/NNG", "조직/NNG", "을/JKO", "구성/NNG", "하/XSV", "었/EP", "다/EF"], ["임호/NNP", "기자/NNG", "tiger/SL", "35/SN", "@/SW", "yeongnamcom/SL"]], "tgt": [["경북도/NNP", "가/JKS", "산/NNG", "·/SP", "학/NNG", "·/SP", "연/NNG", "·/SP", "관/NNG", "이/JKS", "참여/NNG", "하/XSV", "는/ETM", "거버넌스/NNG", "조직/NNG", "을/JKO", "구성/NNG", "하/XSV", "어/EC", "5/SN", "차/NNB", "산업/NNG", "의/JKG", "핵심/NNG", "이/VCP", "ㄴ/ETM", "바이오/NNG", "생명/NNG", "산업/NNG", "육성/NNG", "에/JKB", "본격/NNG", "나서/VV", "ㄴ다/EF"], ["협의/NNG", "체/XSN", "는/JX", "기관/NNG", "별/XSN", "업무/NNG", "특성/NNG", "과/JC", "전문/NNG", "성/XSN", "에/JKB", "따르/VV", "어/EC", "△/SW", "백신/NNG", "·/SP", "신약/NNG", "△/SW", "식품/NNG", "·/SP", "생명/NNG", "기술/NNG", "△/SW", "한방/NNG", "·/SP", "테라피/NNP", "·/SP", "웰빙/NNG", "등/NNB", "3/SN", "개/NNB", "분야/NNG", "로/JKB", "운영/NNG", "되/XSV", "ㄴ다/EF"], ["도/NNG", "가/JKS", "생명/NNG", "산업/NNG", "에/JKB", "적극/NNG", "적/XSN", "이/VCP", "ㄴ/ETM", "것/NNB", "은/JX", "선진/NNG", "국/XSN", "이/JKS", "이미/MAG", "생명/NNG", "의학/NNG", "(/SS", "줄기/NNG", "세포/NNG", ")/SS", "·/SP", "바이오/NNG", "에너지/NNG", ",/SP", "비/XPN", "식품/NNG", "바이오/NNG", "기술/NNG", ",/SP", "재생/NNG", "의료/NNG", "등/NNB", "‘/SS", "바이오/NNG", "경제/NNG", "시대/NNG", "’/SS", "를/JKO", "준비/NNG", "하/XSV", "고/EC", "있/VX", "기/ETN", "때문/NNB", "이/VCP", "다/EF"]]}]