[{"src": [["국토/NNG", "교통/NNG", "부/NNG", "‘/SS", "지역/NNG", "수요/NNG", "맞춤/NNG", "지원/NNG", "’/SS", "공모/NNG", "에서/JKB", "경북도/NNP", "내/NNB", "7/SN", "개/NNB", "사업/NNG", "이/JKS", "선정/NNG", "되/XSV", "어/EC", "국비/NNG", "119/SN", "억/NR", "원/NNB", "을/JKO", "확보/NNG", "하/XSV", "었/EP", "다/EF"], ["먼저/MAG", "경북도/NNP", "는/JX", "이번/NNG", "공모/NNG", "사업/NNG", "선정/NNG", "에/JKB", "따르/VV", "어/EC", "영주시/NNP", "봉현면/NNP", "오현리/NNP", "에/JKB", "‘/SS", "500/SN", "년/NNB", "풍기/NNG", "인삼/NNG", "문화/NNG", "팝/NNG", "업/NNG", "공원/NNG", "’/SS", "을/JKO", "조성/NNG", "하/XSV", "ㄴ다/EF"], ["문경시/NNP", "돌리/NNP", "네/XSN", "습지/NNG", "주변/NNG", "에/JKB", "는/JX", "사업/NNG", "비/XSN", "27/SN", "억/NR", "원/NNB", "(/SS", "국비/NNG", "19/SN", "억/NR", "원/NNB", ",/SP", "지방/NNG", "비/XSN", "8/SN", "억/NR", "원/NNB", ")/SS", "을/JKO", "투자/NNG", "하/XSV", "어/EC", "도로/NNG", ",/SP", "산책/NNG", "로/JKB", ",/SP", "주차/NNG", "장/XSN", ",/SP", "소/XPN", "공원/NNG", "을/JKO", "만들/VV", "고/EC", "로컬/NNG", "푸드/NNG", "카페/NNG", ",/SP", "체험/NNG", "프로그램/NNG", "등/NNB", "을/JKO", "운영/NNG", "하/XSV", "ㄴ다/EF"], ["또/MAG", "울릉군/NNP", "은/JX", "국비/NNG", "20/SN", "억/NR", "원/NNB", "을/JKO", "투입/NNG", "하/XSV", "어/EC", "차량/NNG", "통행/NNG", "이/JKS", "가장/MAG", "많/VA", "은/ETM", "도동/NNG", "에/JKB", "주차/NNG", "장/XSN", "을/JKO", "만들/VV", "ㄴ다/EF"], ["최대지/NNG", "ㄴ/JX", "도/NNG", "건설/NNG", "도시/NNG", "국장/NNG", "은/JX", "“/SS", "이번/NNG", "공모/NNG", "사업/NNG", "은/JX", "많/VA", "은/ETM", "예산/NNG", "이/JKS", "들/VV", "는/ETM", "대/XPN", "규모/NNG", "개발/NNG", "사업/NNG", "보다/JKB", "는/JX", "적/VA", "은/ETM", "비용/NNG", "으로/JKB", "주민/NNG", "이/JKS", "직접/MAG", "혜택/NNG", "을/JKO", "보/VV", "는/ETM", "데/NNB", "중점/NNG", "을/JKO", "두/VV", "었/EP", "다/EF", "”/SS", "며/EC", "“/SS", "소/XPN", "규모/NNG", "기반/NNG", "시설/NNG", "신설/NNG", "·/SP", "정비/NNG", ",/SP", "체험/NNG", "관광/NNG", "등/NNB", "으로/JKB", "주민/NNG", "삶/NNG", "의/JKG", "질/NNG", "향상/NNG", "과/JC", "지역/NNG", "경제/NNG", "활성/NNG", "화/XSN", "에/JKB", "도움/NNG", "이/JKC", "되/VV", "ㄹ/ETM", "것/NNB", "으로/JKB", "기대/NNG", "하/XSV", "ㄴ다/EF", "”/SS", "고/JKQ", "말/NNG", "하/XSV", "었/EP", "다/EF"], ["임호/NNP", "기자/NNG", "tiger/SL", "35/SN", "@/SW", "yeongnamcom/SL"]], "tgt": [["국토/NNG", "교통/NNG", "부/NNG", "‘/SS", "지역/NNG", "수요/NNG", "맞춤/NNG", "지원/NNG", "’/SS", "공모/NNG", "에서/JKB", "경북도/NNP", "내/NNB", "7/SN", "개/NNB", "사업/NNG", "이/JKS", "선정/NNG", "되/XSV", "어/EC", "국비/NNG", "119/SN", "억/NR", "원/NNB", "을/JKO", "확보/NNG", "하/XSV", "었/EP", "다/EF"], ["문경시/NNP", "돌리/NNP", "네/XSN", "습지/NNG", "주변/NNG", "에/JKB", "는/JX", "사업/NNG", "비/XSN", "27/SN", "억/NR", "원/NNB", "(/SS", "국비/NNG", "19/SN", "억/NR", "원/NNB", ",/SP", "지방/NNG", "비/XSN", "8/SN", "억/NR", "원/NNB", ")/SS", "을/JKO", "투자/NNG", "하/XSV", "어/EC", "도로/NNG", ",/SP", "산책/NNG", "로/JKB", ",/SP", "주차/NNG", "장/XSN", ",/SP", "소/XPN", "공원/NNG", "을/JKO", "만들/VV", "고/EC", "로컬/NNG", "푸드/NNG", "카페/NNG", ",/SP", "체험/NNG", "프로그램/NNG", "등/NNB", "을/JKO", "운영/NNG", "하/XSV", "ㄴ다/EF"]]}, {"src": [["포스코/NNP", "가/JKS", "국내/NNG", "기업/NNG", "으로/JKB", "ㄴ/JX", "처음/NNG", "으로/JKB", "세계/NNG", "경제/NNG", "포럼/NNG", "(/SS", "일명/NNG", "다보스/NNP", "포럼/NNG", ")/SS", "의/JKG", "‘/SS", "등대/NNG", "공장/NNG", "(/SS", "Lighthouse/SL", "factory/SL", ")/SS", "’/SS", "으로/JKB", "선정/NNG", "되/XSV", "었/EP", "다/EF"], ["세계/NNG", "경제/NNG", "포럼/NNG", "은/JX", "지난해/NNG", "부터/JX", "등대/NNG", "공장/NNG", "을/JKO", "발표/NNG", "하/XSV", "어/EC", "오/VX", "고/EC", "있/VX", "으며/EC", ",/SP", "전/MM", "세계/NNG", "공장/NNG", "을/JKO", "대상/NNG", "으로/JKB", "심사/NNG", "하/XSV", "어/EC", "매년/MAG", "두/MM", "차례/NNG", "선정/NNG", "하/XSV", "ㄹ/ETM", "계획/NNG", "이/VCP", "다/EF"], ["포스코/NNP", "는/JX", "지나/VV", "ㄴ/ETM", "50/SN", "년/NNB", "간/XSN", "축적/NNG", "되/XSV", "ㄴ/ETM", "현장/NNG", "경험/NNG", "과/JC", "노/NNG", "하우/NNG", "를/JKO", "바탕/NNG", "으로/JKB", "사물/NNG", "인터넷/NNG", "·/SP", "인공/NNG", "지능/NNG", "·/SP", "빅/NNG", "데이터/NNG", "등/NNB", "을/JKO", "전/MM", "생산/NNG", "공정/NNG", "에/JKB", "접목/NNG", "하/XSV", "어/EC", "최적/NNG", "의/JKG", "생산/NNG", "현장/NNG", "을/JKO", "구현/NNG", "하/XSV", "고/EC", "있/VX", "다/EF"], ["포항/NNP", "=/SW", "마창성/NNP", "기자/NNG", "mcs/SL", "12/SN", "@/SW", "yeongnamcom/SL"]], "tgt": [["포스코/NNP", "가/JKS", "국내/NNG", "기업/NNG", "으로/JKB", "ㄴ/JX", "처음/NNG", "으로/JKB", "세계/NNG", "경제/NNG", "포럼/NNG", "(/SS", "일명/NNG", "다보스/NNP", "포럼/NNG", ")/SS", "의/JKG", "‘/SS", "등대/NNG", "공장/NNG", "(/SS", "Lighthouse/SL", "factory/SL", ")/SS", "’/SS", "으로/JKB", "선정/NNG", "되/XSV", "었/EP", "다/EF"], ["세계/NNG", "경제/NNG", "포럼/NNG", "은/JX", "지난해/NNG", "부터/JX", "등대/NNG", "공장/NNG", "을/JKO", "발표/NNG", "하/XSV", "어/EC", "오/VX", "고/EC", "있/VX", "으며/EC", ",/SP", "전/MM", "세계/NNG", "공장/NNG", "을/JKO", "대상/NNG", "으로/JKB", "심사/NNG", "하/XSV", "어/EC", "매년/MAG", "두/MM", "차례/NNG", "선정/NNG", "하/XSV", "ㄹ/ETM", "계획/NNG", "이/VCP", "다/EF"], ["포스코/NNP", "는/JX", "지나/VV", "ㄴ/ETM", "50/SN", "년/NNB", "간/XSN", "축적/NNG", "되/XSV", "ㄴ/ETM", "현장/NNG", "경험/NNG", "과/JC", "노/NNG", "하우/NNG", "를/JKO", "바탕/NNG", "으로/JKB", "사물/NNG", "인터넷/NNG", "·/SP", "인공/NNG", "지능/NNG", "·/SP", "빅/NNG", "데이터/NNG", "등/NNB", "을/JKO", "전/MM", "생산/NNG", "공정/NNG", "에/JKB", "접목/NNG", "하/XSV", "어/EC", "최적/NNG", "의/JKG", "생산/NNG", "현장/NNG", "을/JKO", "구현/NNG", "하/XSV", "고/EC", "있/VX", "다/EF"]]}, {"src": [["정부/NNG", "가/JKS", "올해/NNG", "한국/NNP", "경제/NNG", "성장/NNG", "률/XSN", "전망/NNG", "치/XSN", "를/JKO", "24/SN", "∼/SO", "25/SN", "%/SW", "로/JKB", "제시/NNG", "하/XSV", "었/EP", "다/EF"], ["정부/NNG", "는/JX", "3/SN", "일/NNB", "정부서울청사/NNP", "에서/JKB", "홍남기/NNP", "경제/NNG", "부/XPN", "총리/NNG", "겸/NNB", "기획/NNG", "재정/NNG", "부/XSN", "장관/NNG", "주재/NNG", "로/JKB", "경제/NNG", "관계/NNG", "장관/NNG", "회의/NNG", "를/JKO", "열/VV", "고/EC", "이/NP", "같/VA", "은/ETM", "내용/NNG", "을/JKO", "담/VV", "은/ETM", "‘/SS", "2019/SN", "년/NNB", "하/NNG", "반기/NNG", "경제/NNG", "정책/NNG", "방향/NNG", "’/SS", "을/JKO", "발표/NNG", "하/XSV", "었/EP", "다/EF"], ["경제/NNG", "정책/NNG", "방향/NNG", "에/JKB", "따르/VV", "면/EC", "올해/NNG", "소비/NNG", "와/JC", "건설/NNG", "·/SP", "설비/NNG", "투자/NNG", "전망/NNG", "치/XSN", "도/JX", "하향/NNG", "조정/NNG", "되/XSV", "었/EP", "다/EF"], ["정부/NNG", "는/JX", "이/NP", "같/VA", "은/ETM", "전망/NNG", "에/JKB", "대하/VV", "어/EC", "효자/NNG", "수출/NNG", "품목/NNG", "이/VCP", "ㄴ/ETM", "반/XPN", "도체/NNG", "의/JKG", "가격/NNG", "이/JKS", "하락/NNG", "하/XSV", "면서/EC", "수출/NNG", "실적/NNG", "이/JKS", "둔화/NNG", "하/XSV", "고/EC", "있/VX", "고/EC", ",/SP", "미국/NNP", "·/SP", "중국/NNP", "간/NNB", "무역/NNG", "갈등/NNG", "이/JKS", "장기/NNG", "화/XSN", "되/XSV", "는/ETM", "등/NNB", "대외/NNG", "여건/NNG", "악화/NNG", "가/JKS", "영향/NNG", "을/JKO", "미치/VV", "ㄴ/ETM", "것/NNB", "으로/JKB", "풀이/NNG", "하/XSV", "었/EP", "다/EF"], ["한편/MAG", "정부/NNG", "는/JX", "내년/NNG", "한국/NNP", "경제/NNG", "전망/NNG", "치/XSN", "도/JX", "이날/NNG", "함께/MAG", "발표/NNG", "하/XSV", "었/EP", "다/EF"], ["정재훈/NNP", "기자/NNG", "jjhoon/SL", "@/SW", "yeongnamcom/SL"]], "tgt": [["정부/NNG", "가/JKS", "올해/NNG", "한국/NNP", "경제/NNG", "성장/NNG", "률/XSN", "전망/NNG", "치/XSN", "를/JKO", "24/SN", "∼/SO", "25/SN", "%/SW", "로/JKB", "제시/NNG", "하/XSV", "었/EP", "다/EF"], ["정부/NNG", "는/JX", "3/SN", "일/NNB", "정부서울청사/NNP", "에서/JKB", "홍남기/NNP", "경제/NNG", "부/XPN", "총리/NNG", "겸/NNB", "기획/NNG", "재정/NNG", "부/XSN", "장관/NNG", "주재/NNG", "로/JKB", "경제/NNG", "관계/NNG", "장관/NNG", "회의/NNG", "를/JKO", "열/VV", "고/EC", "이/NP", "같/VA", "은/ETM", "내용/NNG", "을/JKO", "담/VV", "은/ETM", "‘/SS", "2019/SN", "년/NNB", "하/NNG", "반기/NNG", "경제/NNG", "정책/NNG", "방향/NNG", "’/SS", "을/JKO", "발표/NNG", "하/XSV", "었/EP", "다/EF"]]}, {"src": [["대구/NNP", "FC/SL", "가/JKS", "오/VV", "는/ETM", "6/SN", "일/NNB", "오후/NNG", "7/SN", "시/NNB", "30/SN", "분/NNB", "DGB/SL", "대구은행파크/NNP", "에서/JKB", "열리/VV", "는/ETM", "경남/NNP", "FC/SL", "와/JKB", "의/JKG", "홈/NNG", "경기/NNG", "에서/JKB", "주장/NNG", "한희훈/NNP", "</SS", "사진/NNG", ">/SS", "을/JKO", "내세우/VV", "ㄴ/ETM", "다양/NNG", "하/XSA", "ㄴ/ETM", "이벤트/NNG", "를/JKO", "열/VV", "ㄴ다/EF"], ["이번/NNG", "경기/NNG", "에/JKB", "도/JX", "한희훈/NNP", "이/JKS", "약속/NNG", "으로/JKB", "경남전/NNP", "승리/NNG", "에/JKB", "힘/NNG", "을/JKO", "보태/VV", "ㄴ다/EF"], ["팬/NNG", "과/JKB", "의/JKG", "스킨십/NNG", "에/JKB", "도/JX", "나서/VV", "ㄴ다/EF"], ["이/MM", "밖/NNG", "에/JKB", "도/JX", "한희훈/NNP", "친필사/NNG", "이/VCP", "ㄴ/ETM", "티셔츠/NNG", "가/JKS", "걸리/VV", "어/EC", "있/VX", "는/ETM", "‘/SS", "약속/NNG", "왕/NNG", "한희훈/NNP", "’/SS", "라이브/NNG", "퀴즈/NNG", "쇼/NNG", "를/JKO", "비롯하/VV", "어/EC", "대팍/NNG", "나이트/NNG", "라이트/NNG", "쇼/NNG", ",/SP", "고바슨/NNP", "음료/NNG", "쿠폰/NNG", "추첨/NNG", "등/NNB", "다양/NNG", "하/XSA", "ㄴ/ETM", "이벤트/NNG", "가/JKS", "준비/NNG", "되/XSV", "어/EC", "있/VX", "다/EF"], ["박진관/NNP", "기자/NNG", "pajika/SL", "@/SW", "yeongnamcom/SL"]], "tgt": [["대구/NNP", "FC/SL", "가/JKS", "오/VV", "는/ETM", "6/SN", "일/NNB", "오후/NNG", "7/SN", "시/NNB", "30/SN", "분/NNB", "DGB/SL", "대구은행파크/NNP", "에서/JKB", "열리/VV", "는/ETM", "경남/NNP", "FC/SL", "와/JKB", "의/JKG", "홈/NNG", "경기/NNG", "에서/JKB", "주장/NNG", "한희훈/NNP", "</SS", "사진/NNG", ">/SS", "을/JKO", "내세우/VV", "ㄴ/ETM", "다양/NNG", "하/XSA", "ㄴ/ETM", "이벤트/NNG", "를/JKO", "열/VV", "ㄴ다/EF"], ["이번/NNG", "경기/NNG", "에/JKB", "도/JX", "한희훈/NNP", "이/JKS", "약속/NNG", "으로/JKB", "경남전/NNP", "승리/NNG", "에/JKB", "힘/NNG", "을/JKO", "보태/VV", "ㄴ다/EF"], ["팬/NNG", "과/JKB", "의/JKG", "스킨십/NNG", "에/JKB", "도/JX", "나서/VV", "ㄴ다/EF"]]}, {"src": [["국제/NNG", "학술/NNG", "대회/NNG", "참가/NNG", "자/XSN", "들/XSN", "이/JKS", "지난달/NNG", "28/SN", "일/NNB", "러시아/NNP", "블라디보스토크/NNP", "에서/JKB", "열리/VV", "ㄴ/ETM", "세미나/NNG", "를/JKO", "마치/VV", "ㄴ/ETM", "뒤/NNG", "기념/NNG", "촬영/NNG", "을/JKO", "하/VV", "고/EC", "있/VX", "다/EF"], ["대한민국/NNP", "임시/NNG", "정부/NNG", "수립/NNG", "100/SN", "주년/NNB", "을/JKO", "맞/VV", "어/EC", "</SS", "사/NNG", ">/SS", "독립/NNG", "운동/NNG", "정신/NNG", "계승/NNG", "사업/NNG", "회/XSN", "(/SS", "상임/NNG", "대표/NNG", "배한동/NNP", ")/SS", "와/JC", "평화/NNG", "통일/NNG", "대구시민연대/NNP", "가/JKS", "공동/NNG", "주최/NNG", "하/XSV", "고/EC", "대구시/NNP", "가/JKS", "후원/NNG", "하/XSV", "ㄴ/ETM", "국제/NNG", "학술/NNG", "대회/NNG", "가/JKS", "지난달/NNG", "28/SN", "일/NNB", "과/JC", "30/SN", "일/NNB", "러시아/NNP", "연해주/NNP", "블라디보스토크시/NNP", "아무지트호텔/NNP", "과/JC", "우수/NNG", "리스크/NNG", "시/NNB", "고려인/NNP", "문화/NNG", "센터/NNG", "에서/JKB", "각각/MAG", "열리/VV", "었/EP", "다/EF"], ["윤덕홍/NNP", "전/MM", "교육/NNG", "부/XPN", "총리/NNG", "의/JKG", "개회/NNG", "사/XSN", "로/JKB", "시작/NNG", "되/XSV", "ㄴ/ETM", "28/SN", "일/NNB", "세미나/NNG", "에서/JKB", "해외/NNG", "동포/NNG", "및/MAJ", "통일/NNG", "문제/NNG", "전문/NNG", "가/XSN", "이/VCP", "ㄴ/ETM", "배한동/NNP", "경북대/NNP", "명예/NNG", "교수/NNG", "는/JX", "‘/SS", "러시아/NNP", "연해주/NNP", "고려/NNP", "인/XSN", "의/JKG", "항일/NNG", "운동/NNG", "의/JKG", "재/XPN", "조명/NNG", "’/SS", "이/VCP", "란/ETM", "주제/NNG", "로/JKB", "기조/NNG", "논문/NNG", "을/JKO", "발표/NNG", "하/XSV", "었/EP", "다/EF"], ["잇/VV", "어/EC", "최정환/NNP", "경북대/NNP", "사학/NNG", "과/NNG", "명예/NNG", "교수/NNG", "가/JKS", "‘/SS", "연해주/NNP", "고려/NNP", "인/XSN", "의/JKG", "역사/NNG", "와/JC", "최재형/NNP", "의/JKG", "항일/NNG", "독립/NNG", "투쟁/NNG", "’/SS", ",/SP", "김정계/NNP", "창원대/NNP", "명예/NNG", "교수/NNG", "가/JKS", "‘/SS", "러시아/NNP", "에서/JKB", "의/JKG", "독립/NNG", "운동/NNG", "과/JC", "상하이/NNP", "임정/NNP", "’/SS", ",/SP", "박진관/NNP", "영남일보/NNP", "기자/NNG", "가/JKS", "‘/SS", "성주/NNP", "한개마을/NNP", "이승희/NNP", "의/JKG", "독립/NNG", "운동/NNG", "(/SS", "러시아/NNP", "연해주/NNP", "에서/JKB", "중국/NNP", "서탑/NNG", "까지/JX", ")/SS", "’/SS", ",/SP", "김두현/NNP", "대구/NNP", "수성구의회/NNP", "의원/NNG", "이/JKS", "‘/SS", "러시아/NNP", "한인/NNG", "사회당/NNP", "과/JC", "이동휘/NNP", "의/JKG", "항일/NNG", "활동/NNG", "’/SS", "을/JKO", "주제/NNG", "로/JKB", "연해주/NNP", "지역/NNG", "의/JKG", "역사/NNG", "와/JC", "이곳/NP", "을/JKO", "중심/NNG", "으로/JKB", "항일/NNG", "운동/NNG", "을/JKO", "펼치/VV", "었/EP", "던/ETM", "독립/NNG", "지사/NNG", "들/XSN", "을/JKO", "조명/NNG", "하/XSV", "었/EP", "다/EF"], ["30/SN", "일/NNB", "에/JKB", "는/JX", "바지/VV", "ㅁ/ETN", "우수/NNG", "리스크/NNG", "시/NNB", "노인협회/NNP", "부/XPN", "회장/NNG", "이/JKS", "‘/SS", "고려인/NNP", "문화/NNG", "센터/NNG", "의/JKG", "역할/NNG", "과/JC", "의의/NNG", "’/SS", "에/JKB", "대하/VV", "어/EC", "특강/NNG", "을/JKO", "하/VV", "었/EP", "다/EF"], ["이번/NNG", "국제/NNG", "학술/NNG", "대회/NNG", "에/JKB", "구순/NNP", "이/JKS", "넘/VV", "은/ETM", "강창덕/NNP", "민주/NNG", "화/XSN", "운동/NNG", "원로/NNG", "회/XSN", "의/JKG", "의장/NNG", "(/SS", "93/SN", ")/SS", ",/SP", "이용수/NNP", "일본/NNP", "군/NNG", "강제/NNG", "위안/NNG", "부/XSN", "할머니/NNG", "(/SS", "92/SN", ")/SS", "가/JKS", "참가/NNG", "하/XSV", "어/EC", "더욱/MAG", "의미/NNG", "가/JKS", "깊/VA", "었/EP", "다/EF"], ["국제/NNG", "학술/NNG", "회/XSN", "대회/NNG", "참가/NNG", "자/XSN", "들/XSN", "은/JX", "3/SN", "박/NNB", "4/SN", "일/NNB", "간/XSN", "블라디보스토크시/NNP", "에/JKB", "있/VA", "는/ETM", "‘/SS", "신한촌/NNP", "기념/NNG", "비/NNG", "’/SS", "와/JC", "크라스키노시/NNP", "내/NNB", "‘/SS", "안중근/NNP", "의사/NNG", "및/MAJ", "11/SN", "인/NNG", "동지/NNG", "의/JKG", "단지/NNG", "동맹/NNG", "유지/NNG", "’/SS", ",/SP", "우스리스크시/NNP", "교외/NNG", "에/JKB", "위치/NNG", "하/XSV", "ㄴ/ETM", "‘/SS", "보재/NNP", "이상설/NNP", "선생/NNG", "유허/NNG", "비/NNG", "’/SS", "‘/SS", "최재형/NNP", "선생/NNG", "옛집/NNG", "’/SS", "등지/NNB", "를/JKO", "찾/VV", "어/EC", "헌화/NNG", "하/XSV", "고/EC", "지사/NNG", "들/XSN", "의/JKG", "독립/NNG", "정신/NNG", "을/JKO", "기리/VV", "었/EP", "다/EF"], ["윤/NNP", "전/MM", "부/XPN", "총리/NNG", "는/JX", "“/SS", "정부/NNG", "와/JC", "보훈/NNG", "처/XSN", "가/JKS", "러시아/NNP", "측/NNB", "과/JKB", "협의/NNG", "하/XSV", "어/EC", "이동휘/NNP", "선생/NNG", "의/JKG", "생가/NNG", "를/JKO", "복원/NNG", "하/XSV", "면/EC", "한국/NNP", "인/XSN", "에게/JKB", "는/JX", "교육/NNG", "의/JKG", "장/NNG", "이/JKC", "되/VV", "ㄹ/ETM", "것/NNB", "이/VCP", "고/EC", ",/SP", "연해주/NNP", "에/JKB", "ㄴ/JX", "또/MAG", "하나/NNG", "의/JKG", "관광/NNG", "명소/NNG", "가/JKS", "생기/VV", "게/EC", "되/VV", "ㄹ/ETM", "것/NNB", "”/SS", "이/VCP", "라며/EC", "“/SS", "생가/NNG", "를/JKO", "복원/NNG", "하/XSV", "ㄹ/ETM", "방법/NNG", "을/JKO", "찾아보/VV", "자/EF", "”/SS", "고/JKQ", "말/NNG", "하/XSV", "었/EP", "다/EF"], ["행사/NNG", "기간/NNG", "중/NNB", "판문점/NNP", "에서/JKB", "남/NNP", "·/SP", "북/NNP", "·/SP", "미/NNP", "정상/NNG", "이/JKS", "만나/VV", "ㄴ/ETM", "소식/NNG", "을/JKO", "접하/VV", "ㄴ/ETM", "참가/NNG", "자/XSN", "들/XSN", "은/JX", "귀국/NNG", "길/NNG", "블라디보스토크/NNP", "공항/NNG", "에서/JKB", "고려/NNG", "항공/NNG", "을/JKO", "이용/NNG", ",/SP", "평양/NNP", "으로/JKB", "가/VV", "는/ETM", "북한/NNP", "측/NNB", "관계/NNG", "자/XSN", "들/XSN", "과/JKB", "조우/NNG", "하/XSV", "어/EC", "악수/NNG", "를/JKO", "나누/VV", "며/EC", "“/SS", "내년/NNG", "에/JKB", "ㄴ/JX", "육로/NNG", "로/JKB", "북한/NNP", "을/JKO", "통하/VV", "어/EC", "러시아/NNP", "로/JKB", "가/VV", "ㄹ/ETM", "수/NNB", "있/VA", "도록/EC", "함께/MAG", "평화/NNG", "통일/NNG", "을/JKO", "위하/VV", "어/EC", "노력/NNG", "하/XSV", "자/EF", "”/SS", "고/JKQ", "말/NNG", "하/XSV", "었/EP", "다/EF"], ["글/NNG", "·/SP", "사진/NNG", "=/SW", "블라디보스토크/NNP", "에서/JKB", "박진관/NNP", "기자/NNG", "pajika/SL", "@/SW", "yeongnamcom/SL"]], "tgt": [["대한민국/NNP", "임시/NNG", "정부/NNG", "수립/NNG", "100/SN", "주년/NNB", "을/JKO", "맞/VV", "어/EC", "</SS", "사/NNG", ">/SS", "독립/NNG", "운동/NNG", "정신/NNG", "계승/NNG", "사업/NNG", "회/XSN", "(/SS", "상임/NNG", "대표/NNG", "배한동/NNP", ")/SS", "와/JC", "평화/NNG", "통일/NNG", "대구시민연대/NNP", "가/JKS", "공동/NNG", "주최/NNG", "하/XSV", "고/EC", "대구시/NNP", "가/JKS", "후원/NNG", "하/XSV", "ㄴ/ETM", "국제/NNG", "학술/NNG", "대회/NNG", "가/JKS", "지난달/NNG", "28/SN", "일/NNB", "과/JC", "30/SN", "일/NNB", "러시아/NNP", "연해주/NNP", "블라디보스토크시/NNP", "아무지트호텔/NNP", "과/JC", "우수/NNG", "리스크/NNG", "시/NNB", "고려인/NNP", "문화/NNG", "센터/NNG", "에서/JKB", "각각/MAG", "열리/VV", "었/EP", "다/EF"], ["잇/VV", "어/EC", "최정환/NNP", "경북대/NNP", "사학/NNG", "과/NNG", "명예/NNG", "교수/NNG", "가/JKS", "‘/SS", "연해주/NNP", "고려/NNP", "인/XSN", "의/JKG", "역사/NNG", "와/JC", "최재형/NNP", "의/JKG", "항일/NNG", "독립/NNG", "투쟁/NNG", "’/SS", ",/SP", "김정계/NNP", "창원대/NNP", "명예/NNG", "교수/NNG", "가/JKS", "‘/SS", "러시아/NNP", "에서/JKB", "의/JKG", "독립/NNG", "운동/NNG", "과/JC", "상하이/NNP", "임정/NNP", "’/SS", ",/SP", "박진관/NNP", "영남일보/NNP", "기자/NNG", "가/JKS", "‘/SS", "성주/NNP", "한개마을/NNP", "이승희/NNP", "의/JKG", "독립/NNG", "운동/NNG", "(/SS", "러시아/NNP", "연해주/NNP", "에서/JKB", "중국/NNP", "서탑/NNG", "까지/JX", ")/SS", "’/SS", ",/SP", "김두현/NNP", "대구/NNP", "수성구의회/NNP", "의원/NNG", "이/JKS", "‘/SS", "러시아/NNP", "한인/NNG", "사회당/NNP", "과/JC", "이동휘/NNP", "의/JKG", "항일/NNG", "활동/NNG", "’/SS", "을/JKO", "주제/NNG", "로/JKB", "연해주/NNP", "지역/NNG", "의/JKG", "역사/NNG", "와/JC", "이곳/NP", "을/JKO", "중심/NNG", "으로/JKB", "항일/NNG", "운동/NNG", "을/JKO", "펼치/VV", "었/EP", "던/ETM", "독립/NNG", "지사/NNG", "들/XSN", "을/JKO", "조명/NNG", "하/XSV", "었/EP", "다/EF"], ["30/SN", "일/NNB", "에/JKB", "는/JX", "바지/VV", "ㅁ/ETN", "우수/NNG", "리스크/NNG", "시/NNB", "노인협회/NNP", "부/XPN", "회장/NNG", "이/JKS", "‘/SS", "고려인/NNP", "문화/NNG", "센터/NNG", "의/JKG", "역할/NNG", "과/JC", "의의/NNG", "’/SS", "에/JKB", "대하/VV", "어/EC", "특강/NNG", "을/JKO", "하/VV", "었/EP", "다/EF"]]}]