[{"src": [["14/SN", "세기/NNG", "흑사/NNG", "병/NNG", "부터/JX", "현대/NNG", "에이즈/NNG", "까지/JX", "역사/NNG", "를/JKO", "바꾸/VV", "ㄴ/ETM", "열/NR", "두/MM", "가지/NNB", "질병/NNG", "소개/NNG"], ["감염/NNG", "병/NNG", "전문/NNG", "가/XSN", "이/VCP", "ㄴ/ETM", "부산대학교/NNP", "의학/NNG", "과/JC", "장철훈/NNP", "교수/NNG", "가/JKS", "질병/NNG", "을/JKO", "통하/VV", "어/EC", "바르/VV", "어/EC", "보/VV", "ㄴ/ETM", "역사/NNG", "서/NNG", "이/VCP", "ㄴ/ETM", "미국/NNP", "어윈/NNP", "W/SL", "셔먼/NNP", "교수/NNG", "의/JKG", "저서/NNG", "『/SS", "세상/NNG", "을/JKO", "바꾸/VV", "ㄴ/ETM", "12/SN", "가지/NNB", "질병/NNG", "』/SS", "을/JKO", "번역/NNG", "ㆍ/SP", "출간/NNG", "하/XSV", "었/EP", "다/EF"], ["부산대학교/NNP", "(/SS", "총장/NNG", "전호환/NNP", ")/SS", "는/JX", "의학/NNG", "과/XSN", "교수/NNG", "이/VCP", "자/EC", "양산부산대학교병원/NNP", "진단/NNG", "검사/NNG", "의학/NNG", "과/XSN", "전문/NNG", "의/NNG", "이/VCP", "ㄴ/ETM", "장철훈/NNP", "교수/NNG", "가/JKS", "미국/NNP", "캘리포니아대학교/NNP", "의/JKG", "어윈/NNG", "W/SL", "셔먼/NNP", "명예/NNG", "교수/NNG", "의/JKG", "『/SS", "세상/NNG", "을/JKO", "바꾸/VV", "ㄴ/ETM", "12/SN", "가지/NNB", "질병/NNG", "』/SS", "(/SS", "부산대학교/NNP", "출판/NNG", "문화/NNG", "원/XSN", ",/SP", "2019715/SN", ")/SS", "의/JKG", "역서/NNG", "를/JKO", "출간/NNG", "하/XSV", "었/EP", "다고/EC", "18/SN", "일/NNB", "밝히/VV", "었/EP", "다/EF"], ["역자/NNG", "이/VCP", "ㄴ/ETM", "장철훈/NNP", "교수/NNG", "는/JX", "부산대/NNP", "의학/NNG", "과/XSN", "를/JKO", "졸업/NNG", "하/XSV", "ㄴ/ETM", "진단/NNG", "검사/NNG", "의학/NNG", "과/XSN", "전문/NNG", "의/NNG", "이/VCP", "다/EF"], ["질병/NNG", "은/JX", "종종/MAG", "인류/NNG", "역사/NNG", "의/JKG", "흐름/NNG", "을/JKO", "바꾸/VV", "어/EC", "놓/VX", "었/EP", "다/EF"], ["이/MM", "책/NNG", "에서/JKB", "는/JX", "수많/VA", "은/ETM", "질병/NNG", "을/JKO", "개괄/NNG", "적/XSN", "으로/JKB", "다루/VV", "기/ETN", "보다/JKB", "는/JX", "역사/NNG", "를/JKO", "바꾸/VV", "었/EP", "고/EC", "대안/NNG", "을/JKO", "모색/NNG", "하/XSV", "는/ETM", "이정/NNG", "표/NNG", "가/JKC", "되/VV", "었/EP", "던/ETM", "열/NR", "두/MM", "가지/NNB", "질병/NNG", "에/JKB", "집중/NNG", "하/XSV", "ㄴ다/EF"], ["1/SN", "장/NNB", "의/JKG", "포르피린/NNG", "증/XSN", "과/JC", "혈우/NNG", "병/NNG", "은/JX", "영국/NNP", "ㆍ/SP", "스페인/NNP", "ㆍ/SP", "독일/NNP", "ㆍ/SP", "러시아/NNP", "ㆍ/SP", "미국/NNP", "의/JKG", "정치/NNG", "사/XSN", "를/JKO", "바꾸/VV", "어/EC", "놓/VX", "었/EP", "다/EF"], ["4/SN", "장/NNG", "에서/JKB", "는/JX", "백신/NNG", "이/JKS", "개발/NNG", "되/XSV", "어/EC", "박멸/NNG", "되/XSV", "ㄴ/ETM", "천연/NNG", "두/NNG", "를/JKO", "소개/NNG", "하/XSV", "ㄴ다/EF"], ["인류/NNG", "는/JX", "이렇/VA", "게/EC", "질병/NNG", "과/JKB", "싸우/VV", "면서/EC", "질병/NNG", "을/JKO", "통제/NNG", "하/XSV", "는/ETM", "법/NNB", "을/JKO", "개발/NNG", "하/XSV", "고/EC", "적용/NNG", "하/XSV", "어/EC", "오/VX", "었/EP", "다/EF"], ["저자/NNG", "는/JX", "이/MM", "질병/NNG", "들/XSN", "에/JKB", "대하/VV", "ㄴ/ETM", "역사적/MM", "통찰/NNG", "로/JKB", "선조/NNG", "들/XSN", "이/JKS", "그/MM", "'/SS", "역병/NNG", "'/SS", "으로부터/JKB", "어떻/VA", "게/EC", "살아남/VV", "었/EP", "고/EC", ",/SP", "우리/NP", "가/JKS", "미래/NNG", "의/JKG", "재앙/NNG", "을/JKO", "어떻/VA", "게/EC", "극복/NNG", "하/XSV", "어야/EC", "하/VX", "ㄹ지/EC", "를/JX", "알/VV", "게/EC", "되/VV", "ㄹ/ETM", "것/NNB", "이/VCP", "라고/EC", "밝히/VV", "고/EC", "있/VX", "다/EF"], ["장철훈/NNP", "교수/NNG", "는/JX", "\"/SS", "2009/SN", "년/NNB", "신종/NNG", "플루/NNG", "의/JKG", "대/XPN", "유행/NNG", "과/JC", "2015/SN", "년/NNB", "중동/NNP", "호흡/NNG", "기/XSN", "증후/NNG", "군/XSN", "의/JKG", "국내/NNG", "전파/NNG", "를/JKO", "겪/VV", "으며/EC", "질병/NNG", "이/JKS", "인류/NNG", "에/JKB", "미치/VV", "는/ETM", "영향/NNG", "을/JKO", "우리/NP", "국민/NNG", "들/XSN", "도/JX", "직접/MAG", "체험/NNG", "하/XSV", "었/EP", "다/EF", "\"/SS", "면서/EC", "\"/SS", "이/MM", "책/NNG", "을/JKO", "통하/VV", "어/EC", "질병/NNG", "통제/NNG", "를/JKO", "위하/VV", "어서/EC", "는/JX", "정부/NNG", "의/JKG", "노력/NNG", "뿐/JX", "만/JX", "아니/VCN", "라/EC", "국민/NNG", "모두/NNG", "의/JKG", "성숙/NNG", "하/XSA", "ㄴ/ETM", "의식/NNG", "과/JC", "행동/NNG", "이/JKS", "반드시/MAG", "필요/NNG", "하/XSA", "다는/ETM", "인식/NNG", "이/JKS", "높아지/VV", "었/EP", "으면/EC", "하/VX", "ㄴ다/EF", "\"/SS", "고/JKQ", "역서/NNG", "출간/NNG", "의/JKG", "소감/NNG", "을/JKO", "전하/VV", "었/EP", "다/EF"], ["디지털/NNG", "본부/NNG", "news/SL", "@/SW", "busancom/SL"]], "tgt": [["감염/NNG", "병/NNG", "전문/NNG", "가/XSN", "이/VCP", "ㄴ/ETM", "부산대학교/NNP", "의학/NNG", "과/JC", "장철훈/NNP", "교수/NNG", "가/JKS", "질병/NNG", "을/JKO", "통하/VV", "어/EC", "바르/VV", "어/EC", "보/VV", "ㄴ/ETM", "역사/NNG", "서/NNG", "이/VCP", "ㄴ/ETM", "미국/NNP", "어윈/NNP", "W/SL", "셔먼/NNP", "교수/NNG", "의/JKG", "저서/NNG", "『/SS", "세상/NNG", "을/JKO", "바꾸/VV", "ㄴ/ETM", "12/SN", "가지/NNB", "질병/NNG", "』/SS", "을/JKO", "번역/NNG", "ㆍ/SP", "출간/NNG", "하/XSV", "었/EP", "다/EF"], ["4/SN", "장/NNG", "에서/JKB", "는/JX", "백신/NNG", "이/JKS", "개발/NNG", "되/XSV", "어/EC", "박멸/NNG", "되/XSV", "ㄴ/ETM", "천연/NNG", "두/NNG", "를/JKO", "소개/NNG", "하/XSV", "ㄴ다/EF"], ["장철훈/NNP", "교수/NNG", "는/JX", "\"/SS", "2009/SN", "년/NNB", "신종/NNG", "플루/NNG", "의/JKG", "대/XPN", "유행/NNG", "과/JC", "2015/SN", "년/NNB", "중동/NNP", "호흡/NNG", "기/XSN", "증후/NNG", "군/XSN", "의/JKG", "국내/NNG", "전파/NNG", "를/JKO", "겪/VV", "으며/EC", "질병/NNG", "이/JKS", "인류/NNG", "에/JKB", "미치/VV", "는/ETM", "영향/NNG", "을/JKO", "우리/NP", "국민/NNG", "들/XSN", "도/JX", "직접/MAG", "체험/NNG", "하/XSV", "었/EP", "다/EF", "\"/SS", "면서/EC", "\"/SS", "이/MM", "책/NNG", "을/JKO", "통하/VV", "어/EC", "질병/NNG", "통제/NNG", "를/JKO", "위하/VV", "어서/EC", "는/JX", "정부/NNG", "의/JKG", "노력/NNG", "뿐/JX", "만/JX", "아니/VCN", "라/EC", "국민/NNG", "모두/NNG", "의/JKG", "성숙/NNG", "하/XSA", "ㄴ/ETM", "의식/NNG", "과/JC", "행동/NNG", "이/JKS", "반드시/MAG", "필요/NNG", "하/XSA", "다는/ETM", "인식/NNG", "이/JKS", "높아지/VV", "었/EP", "으면/EC", "하/VX", "ㄴ다/EF", "\"/SS", "고/JKQ", "역서/NNG", "출간/NNG", "의/JKG", "소감/NNG", "을/JKO", "전하/VV", "었/EP", "다/EF"]]}, {"src": [["직업/NNG", "체험/NNG", "프로그램/NNG", "활동/NNG", "및/MAJ", "단체/NNG", "사진/NNG", "(/SS", "좌측/NNG", "상단/NNG", ":/SP", "대연중/NNG", ",/SP", "우측/NNG", "상단/NNG", ":/SP", "용호중/NNP", ",/SP", "좌/NNG", "ㆍ/SP", "우측/NNG", "하단/NNG", ":/SP", "만덕고/NNP", ")/SS"], ["경성대학교/NNP", "(/SS", "총장/NNG", "송수건/NNG", ")/SS", "중앙/NNG", "도서/NNG", "관/XSN", "은/JX", "부산/NNP", "지역/NNG", "중/NNG", "？/SF", "？/SF", "고등/NNG", "학교/NNG", "학생/NNG", "들/XSN", "을/JKO", "대상/NNG", "으로/JKB", "사/VV", "어서/EC", "직업/NNG", "체험/NNG", "프로그램/NNG", "을/JKO", "진행/NNG", "하/XSV", "었/EP", "다/EF"], ["이/MM", "프로그램/NNG", "은/JX", "대학/NNG", "도서/NNG", "관/XSN", "의/JKG", "지역/NNG", "사회/NNG", "연계/NNG", "와/JC", "교류/NNG", "협력/NNG", "강화/NNG", "의/JKG", "일환/NNG", "으로/JKB", ",/SP", "중/NNG", "ㆍ/SP", "고등/NNG", "학생/NNG", "들/XSN", "을/JKO", "대상/NNG", "으로/JKB", "도서/NNG", "관/XSN", "운영/NNG", "및/MAJ", "사서/NNG", "에/JKB", "관하/VV", "ㄴ/ETM", "이론/NNG", "과/JC", "실습/NNG", "을/JKO", "통하/VV", "어/EC", "사/VV", "어서/EC", "직업/NNG", "체험/NNG", "기회/NNG", "를/JKO", "제공/NNG", "하/XSV", "기/ETN", "위하/VV", "어/EC", "시행/NNG", "되/XSV", "었/EP", "다/EF"], ["지나/VV", "ㄴ/ETM", "6,7/SN", "월/NNB", "에/JKB", "용호중학교/NNP", ",/SP", "만덕/NNP", "고등/NNG", "학교/NNG", ",/SP", "대연/NNG", "중/NNG", "학교/NNG", "학생/NNG", "약/MM", "90/SN", "여/XSN", "명/NNB", "이/JKS", "참여/NNG", "하/XSV", "었/EP", "으며/EC", "도서/NNG", "관/XSN", "사/VV", "어서/EC", "진로/NNG", "에/JKB", "대하/VV", "ㄴ/ETM", "안내/NNG", "와/JC", "도서/NNG", "관/XSN", "전반/NNG", "에/JKB", "대하/VV", "ㄴ/ETM", "설명/NNG", ",/SP", "사/VV", "어서/EC", "멘토/NNG", "들/XSN", "과/JKB", "한국십진/NNP", "분류/NNG", "방법/NNG", "에/JKB", "따르/VV", "ㄴ/ETM", "도서/NNG", "구분/NNG", "을/JKO", "통하/VV", "어/EC", "직업/NNG", "현장/NNG", "시간/NNG", "을/JKO", "가지/VV", "었/EP", "다/EF"], ["사/VV", "어서/EC", "체험/NNG", "후/NNG", "설문/NNG", "지/XSN", "에/JKB", "소감/NNG", "을/JKO", "적/VV", "어/EC", "학생/NNG", "들/XSN", "과/JKB", "사/VV", "어서/EC", "간/NNB", "의/JKG", "경험/NNG", "을/JKO", "공유/NNG", "하/XSV", "는/ETM", "시간/NNG", "을/JKO", "가지기/VV", "기/ETN", "도/JX", "하/VX", "었/EP", "다/EF"], ["사/VV", "어서/EC", "체험/NNG", "프로그램/NNG", "은/JX", "2020/SN", "년/NNB", "2/SN", "월/NNB", "까지/JX", "지속/NNG", "되/VV", "ㄹ/ETM", "예정/NNG", "이/VCP", "며/EC", ",/SP", "참여/NNG", "를/JKO", "희망/NNG", "하/XSV", "는/ETM", "학교/NNG", "는/JX", "경성대학교/NNP", "중앙/NNG", "도서/NNG", "관/XSN", "으로/JKB", "문의/NNG", "가/JKS", "가능/NNG", "하/XSA", "다/EF"], ["중앙/NNG", "도서/NNG", "관/XSN", "정규석/NNP", "관장/NNG", "은/JX", "\"/SS", "자유/NNG", "학기/NNG", "제/XSN", "및/MAJ", "지역/NNG", "사회/NNG", "와/JKB", "연계/NNG", "하/XSV", "어/EC", "의미/NNG", "있/VA", "는/ETM", "프로그램/NNG", "을/JKO", "지속/NNG", "적/XSN", "으로/JKB", "개발/NNG", "하/XSV", "ㄹ/ETM", "예정/NNG", "이/VCP", "다/EF", "\"/SS", "며/EC", "\"/SS", "이번/NNG", "사/VV", "어서/EC", "직업/NNG", "체험/NNG", "을/JKO", "통하/VV", "어/EC", "도서/NNG", "관/XSN", "에/JKB", "대하/VV", "ㄴ/ETM", "관심/NNG", "을/JKO", "높이/VV", "며/EC", ",/SP", "대학/NNG", "도서/NNG", "관/XSN", "이/JKS", "지역/NNG", "사회/NNG", "중/NNG", "ㆍ/SP", "고등/NNG", "학생/NNG", "들/XSN", "의/JKG", "진로/NNG", "관련/NNG", "교육/NNG", "콘텐츠/NNG", "를/JKO", "제공/NNG", "하/XSV", "고/EC", "지원/NNG", "하/XSV", "ㄹ/ETM", "수/NNB", "있/VA", "는/ETM", "직업/NNG", "체험/NNG", "의/JKG", "장/NNG", "이/JKC", "되/VV", "기/ETN", "ㄹ/JKO", "바라/VV", "ㄴ다/EF", "\"/SS", "고/JKQ", "말/NNG", "하/XSV", "었/EP", "다/EF"], ["디지털/NNG", "본부/NNG", "news/SL", "@/SW", "busancom/SL"]], "tgt": [["이/MM", "프로그램/NNG", "은/JX", "대학/NNG", "도서/NNG", "관/XSN", "의/JKG", "지역/NNG", "사회/NNG", "연계/NNG", "와/JC", "교류/NNG", "협력/NNG", "강화/NNG", "의/JKG", "일환/NNG", "으로/JKB", ",/SP", "중/NNG", "ㆍ/SP", "고등/NNG", "학생/NNG", "들/XSN", "을/JKO", "대상/NNG", "으로/JKB", "도서/NNG", "관/XSN", "운영/NNG", "및/MAJ", "사서/NNG", "에/JKB", "관하/VV", "ㄴ/ETM", "이론/NNG", "과/JC", "실습/NNG", "을/JKO", "통하/VV", "어/EC", "사/VV", "어서/EC", "직업/NNG", "체험/NNG", "기회/NNG", "를/JKO", "제공/NNG", "하/XSV", "기/ETN", "위하/VV", "어/EC", "시행/NNG", "되/XSV", "었/EP", "다/EF"], ["지나/VV", "ㄴ/ETM", "6,7/SN", "월/NNB", "에/JKB", "용호중학교/NNP", ",/SP", "만덕/NNP", "고등/NNG", "학교/NNG", ",/SP", "대연/NNG", "중/NNG", "학교/NNG", "학생/NNG", "약/MM", "90/SN", "여/XSN", "명/NNB", "이/JKS", "참여/NNG", "하/XSV", "었/EP", "으며/EC", "도서/NNG", "관/XSN", "사/VV", "어서/EC", "진로/NNG", "에/JKB", "대하/VV", "ㄴ/ETM", "안내/NNG", "와/JC", "도서/NNG", "관/XSN", "전반/NNG", "에/JKB", "대하/VV", "ㄴ/ETM", "설명/NNG", ",/SP", "사/VV", "어서/EC", "멘토/NNG", "들/XSN", "과/JKB", "한국십진/NNP", "분류/NNG", "방법/NNG", "에/JKB", "따르/VV", "ㄴ/ETM", "도서/NNG", "구분/NNG", "을/JKO", "통하/VV", "어/EC", "직업/NNG", "현장/NNG", "시간/NNG", "을/JKO", "가지/VV", "었/EP", "다/EF"], ["사/VV", "어서/EC", "체험/NNG", "후/NNG", "설문/NNG", "지/XSN", "에/JKB", "소감/NNG", "을/JKO", "적/VV", "어/EC", "학생/NNG", "들/XSN", "과/JKB", "사/VV", "어서/EC", "간/NNB", "의/JKG", "경험/NNG", "을/JKO", "공유/NNG", "하/XSV", "는/ETM", "시간/NNG", "을/JKO", "가지기/VV", "기/ETN", "도/JX", "하/VX", "었/EP", "다/EF"]]}, {"src": [["여름/NNG", "햇전어/NNG", ",/SP", "육질/NNG", "연하/VA", "고/EC", "뼈/NNG", "부드럽/VA", "어/EC", "횟/NNG", "감/NNG", "즐기/VV", "는/ETM", "미식/NNG", "가/XSN", "유혹/NNG"], ["‘/SS", "햇/NNG", "전/VV", "어/EC", "나오/VV", "었/EP", "어요/EF", "’/SS"], ["15/SN", "일/NNB", "까지/JX", "금어/NNG", "기/XSN", "를/JKO", "끝내/VV", "ㄴ/ETM", "햇전어/NNG", "가/JKS", "경남/NNP", "사천시/NNP", "팔포항/NNP", "과/JC", "하동군/NNP", "중평/NNP", ",/SP", "술/NNG", "상/NNG", "마을/NNG", "일대/NNG", "에서/JKB", "본격/NNG", "출하/NNG", "되/XSV", "기/ETN", "시작/NNG", "하/XSV", "었/EP", "다/EF"], ["경남/NNP", "사천시/NNP", "는/JX", "오/VV", "는/ETM", "24/SN", "일/NNB", "부터/JX", "28/SN", "일/NNB", "까지/JX", "삼천포항/NNP", "팔포/NNG", "음식/NNG", "특화/NNG", "지구/NNG", "일원/NNG", "에서/JKB", "‘/SS", "제/XPN", "18/SN", "회/NNB", "사천시/NNP", "삼천포항/NNP", "자연/NNG", "산/XSN", "전어/NNG", "축제/NNG", "’/SS", "를/JKO", "열/VV", "ㄴ다고/EC", "18/SN", "일/NNB", "밝히/VV", "었/EP", "다/EF"], ["사천시/NNP", "삼천포/NNP", "앞/NNG", "바다/NNG", "는/JX", "바닷/NNG", "물/NNG", "흐름/NNG", "이/JKS", "빠르/VA", "고/EC", "먹이/NNG", "생물/NNG", "이/JKS", "풍부하/VA", "어/EC", "전어/NNG", "육질/NNG", "이/JKS", "쫄깃하/VA", "고/EC", "맛/NNG", "이/JKS", "좋/VA", "기/ETN", "로/JKB", "유명/NNG", "하/XSA", "다/EF"], ["전어/NNG", "는/JX", "회/NNG", ",/SP", "무침/NNG", ",/SP", "구이/NNG", ",/SP", "회/NNG", "덮밥/NNG", "등/NNB", "으로/JKB", "요리/NNG", "되/XSV", "어/EC", "식객/NNG", "들/XSN", "의/JKG", "입맛/NNG", "을/JKO", "사로잡/VV", "는다/EF"], ["인근/NNG", "하동군/NNP", "에서/JKB", "도/JX", "싱싱/MAG", "하/XSA", "ㄴ/ETM", "전어/NNG", "를/JKO", "어촌/NNG", "현장/NNG", "에서/JKB", "팔/VV", "는/ETM", "판매/NNG", "장/XSN", "이/JKS", "문/NNG", "을/JKO", "열/VV", "었/EP", "다/EF"], ["하동군/NNP", "금남면/NNP", "중평마을/NNP", "어촌/NNG", "계/XSN", "는/JX", "16/SN", "일/NNB", "부터/JX", "전/VV", "어/EC", "조업/NNG", "에/JKB", "나/VV", "서/EC", "하루/NNG", "평균/NNG", "500/SN", "㎏/SW", "을/JKO", "어획/NNG", ",/SP", "찾아오/VV", "는/ETM", "고객/NNG", "들/XSN", "에게/JKB", "팔/VV", "고/EC", "있/VX", "다/EF"], ["판매/NNG", "장/XSN", "에서/JKB", "는/JX", "전어/NNG", "통마리/NNG", ",/SP", "회/NNG", ",/SP", "회/NNG", "무침/NNG", ",/SP", "구이/NNG", "등/NNB", "전어/NNG", "요리/NNG", "와/JC", "왕/XPN", "새우/NNG", "소금/NNG", "구이/NNG", "를/JKO", "저렴하/VA", "ㄴ/ETM", "가격/NNG", "에/JKB", "맛보/VV", "ㄹ/ETM", "수/NNB", "있/VA", "다/EF"], ["하동/NNP", "진교면/NNP", "술상어촌/NNG", "계/XSN", "는/JX", "19/SN", "일/NNB", "부터/JX", "10/SN", "여/XSN", "척/NNB", "의/JKG", "선단/NNG", "이/JKS", "술/NNG", "상/NNG", "앞/NNG", "바다/NNG", "에서/JKB", "전/VV", "어/EC", "조업/NNG", "에/JKB", "본격/NNG", "나서/VV", "ㄴ다/EF"], ["햇전어/NNG", "회/NNG", "와/JC", "전어/NNG", "구이/NNG"], ["사천시/NNP", "삼천포/NNP", "팔포항/NNP", "일대/NNG", "에서/JKB", "열리/VV", "는/ETM", "전어/NNG", "축제/NNG", "광경/NNG"]], "tgt": [["15/SN", "일/NNB", "까지/JX", "금어/NNG", "기/XSN", "를/JKO", "끝내/VV", "ㄴ/ETM", "햇전어/NNG", "가/JKS", "경남/NNP", "사천시/NNP", "팔포항/NNP", "과/JC", "하동군/NNP", "중평/NNP", ",/SP", "술/NNG", "상/NNG", "마을/NNG", "일대/NNG", "에서/JKB", "본격/NNG", "출하/NNG", "되/XSV", "기/ETN", "시작/NNG", "하/XSV", "었/EP", "다/EF"], ["경남/NNP", "사천시/NNP", "는/JX", "오/VV", "는/ETM", "24/SN", "일/NNB", "부터/JX", "28/SN", "일/NNB", "까지/JX", "삼천포항/NNP", "팔포/NNG", "음식/NNG", "특화/NNG", "지구/NNG", "일원/NNG", "에서/JKB", "‘/SS", "제/XPN", "18/SN", "회/NNB", "사천시/NNP", "삼천포항/NNP", "자연/NNG", "산/XSN", "전어/NNG", "축제/NNG", "’/SS", "를/JKO", "열/VV", "ㄴ다고/EC", "18/SN", "일/NNB", "밝히/VV", "었/EP", "다/EF"], ["사천시/NNP", "삼천포/NNP", "앞/NNG", "바다/NNG", "는/JX", "바닷/NNG", "물/NNG", "흐름/NNG", "이/JKS", "빠르/VA", "고/EC", "먹이/NNG", "생물/NNG", "이/JKS", "풍부하/VA", "어/EC", "전어/NNG", "육질/NNG", "이/JKS", "쫄깃하/VA", "고/EC", "맛/NNG", "이/JKS", "좋/VA", "기/ETN", "로/JKB", "유명/NNG", "하/XSA", "다/EF"]]}, {"src": [["진주시/NNP", "·/SP", "GS/SL", "리테일/NNG", ",/SP", "상생/NNG", "협력/NNG", "발전/NNG", "협약/NNG", "체결/NNG", "|/SW", "|/SW", "우선/MAG", "경남/NNP", "지역/NNG", "678/SN", "개/NNB", "편의/NNG", "점/XSN", "에서/JKB", "시작/NNG"], ["진주남강유등/NNP", "축제/NNG", "의/JKG", "명물/NNG", "볼거리/NNG", "이/VCP", "자/EC", "대표/NNG", "적/XSN", "이/VCP", "ㄴ/ETM", "시민/NNG", "참여/NNG", "프로그램/NNG", "이/VCP", "ㄴ/ETM", "‘/SS", "소망/NNG", "등/NNB", "달/VV", "기/ETN", "’/SS", "신청/NNG", "접수/NNG", "가/JKS", "경남/NNP", "지역/NNG", "GS/SL", "25/SN", "편의/NNG", "점/XSN", "에서/JKB", "도/JX", "가능/NNG", "하/XSA", "게/EC", "되/VV", "었/EP", "다/EF"], ["경남/NNP", "진주시/NNP", "와/JC", "GS/SL", "리테일/NNG", "측/NNB", "은/JX", "17/SN", "일/NNB", "진주시청/NNP", "5/SN", "층/NNG", "기업/NNG", "인/XSN", "의/JKG", "방/NNG", "에서/JKB", "진주남강유등/NNP", "축제/NNG", "상생/NNG", "협력/NNG", "발전/NNG", "업무/NNG", "협약/NNG", "(/SS", "MOU/SL", ")/SS", "을/JKO", "체결/NNG", "하/XSV", "었/EP", "다/EF"], ["이/MM", "협약/NNG", "에/JKB", "따르/VV", "어/EC", "경남/NNP", "지역/NNG", "에서/JKB", "영업/NNG", "중/NNB", "이/VCP", "ㄴ/ETM", "678/SN", "개/NNB", "의/JKG", "GS/SL", "25/SN", "에서/JKB", "오/VV", "는/ETM", "24/SN", "일/NNB", "부터/JX", "8/SN", "월/NNB", "31/SN", "일/NNB", "까지/JX", "진주남강/NNP", "유등/NNG", "축제/NNG", "‘/SS", "소망/NNG", "등/NNB", "달/VV", "기/ETN", "’/SS", "신청/NNG", "접수/NNG", "가/JKS", "가능/NNG", "하/XSA", "다/EF"], ["이날/NNG", "조규일/NNP", "진주/NNG", "시장/NNG", "은/JX", "“/SS", "일상/NNG", "생활/NNG", "에/JKB", "가장/MAG", "밀접/NNG", "하/XSA", "ㄴ/ETM", "편의/NNG", "점/XSN", "에서/JKB", "누구/NP", "나/JX", "쉽/VA", "게/EC", "축제/NNG", "에/JKB", "참여/NNG", "하/XSV", "ㄹ/ETM", "수/NNB", "있/VA", "도록/EC", "소망/NNG", "등/NNB", "달/VV", "기/ETN", "신청/NNG", "을/JKO", "편의/NNG", "점/XSN", "상품/NNG", "으로/JKB", "등록/NNG", "하/XSV", "는/ETM", "것/NNB", "은/JX", "일종/NNG", "의/JKG", "발상/NNG", "의/JKG", "전환/NNG", "”/SS", "이/VCP", "라며/EC", "“/SS", "앞/NNG", "으로/JKB", "진주남강/NNP", "유등/NNG", "축제/NNG", "가/JKS", "365/SN", "일/NNB", "대한민국/NNP", "어디/NP", "서/JKB", "나/JX", "함께/MAG", "하/XSV", "기/ETN", "ㄹ/JKO", "바라/VV", "ㄴ다/EF", "”/SS", "고/JKQ", "말/NNG", "하/XSV", "었/EP", "다/EF"], ["박진서/NNP", "GS/SL", "리테일/NNP", "상무/NNG", "는/JX", "“/SS", "진주남강유등/NNP", "축제/NNG", "가/JKS", "세계/NNG", "적/XSN", "이/VCP", "ㄴ/ETM", "축제/NNG", "로/JKB", "발전/NNG", "하/XSV", "기/ETN", "를/JKO", "기원/NNG", "하/XSV", "ㄴ다/EF", "”/SS", "며/EC", "“/SS", "진주남강유등/NNP", "축제/NNG", "와/JC", "라이프/NNG", "스타일/NNG", "플랫폼/NNG", "GS/SL", "25/SN", "가/JKS", "함께/MAG", "성장/NNG", "하/XSV", "고/EC", "발전/NNG", "하/XSV", "ㄹ/ETM", "수/NNB", "있/VA", "도록/EC", "적극/NNG", "협력/NNG", "하/XSV", "겠/EP", "다/EF", "”/SS", "고/JKQ", "말/NNG", "하/XSV", "었/EP", "다/EF"], ["GS/SL", "25/SN", "의/JKG", "라이프/NNG", "스타일/NNG", "플랫폼/NNG", "은/JX", "지역/NNG", "특산/NNG", "품/XSN", "등/NNB", "다양/NNG", "하/XSA", "ㄴ/ETM", "제품/NNG", "을/JKO", "편의/NNG", "점/XSN", "상품/NNG", "으로/JKB", "등록/NNG", "하/XSV", "어/EC", "판매/NNG", "하/XSV", "는/ETM", "시스템/NNG", "이/VCP", "다/EF"], ["문화/NNG", "관광/NNG", "체육/NNG", "부/XSN", "지정/NNG", ",/SP", "우리/NP", "나라/NNG", "최/XPN", "우수/NNG", "축제/NNG", ",/SP", "대한민국/NNP", "대표/NNG", "축제/NNG", "등/NNB", "을/JKO", "거치/VV", "어/EC", "글로벌/NNG", "육성/NNG", "축제/NNG", "가/JKC", "되/VV", "ㄴ/ETM", "진주남강유등/NNP", "축제/NNG", "는/JX", "오/VV", "는/ETM", "10/SN", "월/NNB", "1/SN", "일/NNB", "부터/JX", "13/SN", "일/NNB", "까지/JX", "진주성/NNP", "과/JC", "남강/NNP", "일원/NNG", "에서/JKB", "열리/VV", "ㄴ다/EF"], ["4/SN", "만/NR", "여/XSN", "개/NNB", "의/JKG", "소망/NNG", "의/JKG", "빛/NNG", "으로/JKB", "조성/NNG", "되/XSV", "는/ETM", "소망/NNG", "등/NNB", "터널/NNG", "은/JX", "진주남강유등/NNP", "축제/NNG", "특유/NNG", "의/JKG", "명물/NNG", "볼거리/NNG", "이/VCP", "자/EC", "대표/NNG", "적/XSN", "시민/NNG", "참여/NNG", "프로그램/NNG", "중/NNB", "하나/NR", "이/VCP", "다/EF"], ["4/SN", "만/NR", "여/XSN", "개/NNB", "의/JKG", "소망/NNG", "의/JKG", "빛/NNG", "으로/JKB", "조성/NNG", "되/XSV", "는/ETM", "소망/NNG", "등/NNB", "터널/NNG", "은/JX", "진주남강유등/NNP", "축제/NNG", "특유/NNG", "의/JKG", "명물/NNG", "볼거리/NNG", "이/VCP", "자/EC", "대표/NNG", "적/XSN", "시민/NNG", "참여/NNG", "프로그램/NNG", "중/NNB", "하나/NR", "이/VCP", "다/EF"], ["소망/NNG", "등/NNB", "터널/NNG", "과/JC", "남강/NNP", "유등/NNG", "축제/NNG", "전경/NNG"]], "tgt": [["진주남강유등/NNP", "축제/NNG", "의/JKG", "명물/NNG", "볼거리/NNG", "이/VCP", "자/EC", "대표/NNG", "적/XSN", "이/VCP", "ㄴ/ETM", "시민/NNG", "참여/NNG", "프로그램/NNG", "이/VCP", "ㄴ/ETM", "‘/SS", "소망/NNG", "등/NNB", "달/VV", "기/ETN", "’/SS", "신청/NNG", "접수/NNG", "가/JKS", "경남/NNP", "지역/NNG", "GS/SL", "25/SN", "편의/NNG", "점/XSN", "에서/JKB", "도/JX", "가능/NNG", "하/XSA", "게/EC", "되/VV", "었/EP", "다/EF"], ["경남/NNP", "진주시/NNP", "와/JC", "GS/SL", "리테일/NNG", "측/NNB", "은/JX", "17/SN", "일/NNB", "진주시청/NNP", "5/SN", "층/NNG", "기업/NNG", "인/XSN", "의/JKG", "방/NNG", "에서/JKB", "진주남강유등/NNP", "축제/NNG", "상생/NNG", "협력/NNG", "발전/NNG", "업무/NNG", "협약/NNG", "(/SS", "MOU/SL", ")/SS", "을/JKO", "체결/NNG", "하/XSV", "었/EP", "다/EF"], ["이날/NNG", "조규일/NNP", "진주/NNG", "시장/NNG", "은/JX", "“/SS", "일상/NNG", "생활/NNG", "에/JKB", "가장/MAG", "밀접/NNG", "하/XSA", "ㄴ/ETM", "편의/NNG", "점/XSN", "에서/JKB", "누구/NP", "나/JX", "쉽/VA", "게/EC", "축제/NNG", "에/JKB", "참여/NNG", "하/XSV", "ㄹ/ETM", "수/NNB", "있/VA", "도록/EC", "소망/NNG", "등/NNB", "달/VV", "기/ETN", "신청/NNG", "을/JKO", "편의/NNG", "점/XSN", "상품/NNG", "으로/JKB", "등록/NNG", "하/XSV", "는/ETM", "것/NNB", "은/JX", "일종/NNG", "의/JKG", "발상/NNG", "의/JKG", "전환/NNG", "”/SS", "이/VCP", "라며/EC", "“/SS", "앞/NNG", "으로/JKB", "진주남강/NNP", "유등/NNG", "축제/NNG", "가/JKS", "365/SN", "일/NNB", "대한민국/NNP", "어디/NP", "서/JKB", "나/JX", "함께/MAG", "하/XSV", "기/ETN", "ㄹ/JKO", "바라/VV", "ㄴ다/EF", "”/SS", "고/JKQ", "말/NNG", "하/XSV", "었/EP", "다/EF"]]}, {"src": [["상담/NNG", "치료/NNG", "학부/NNG", "미술/NNG", "치료/NNG", "학/XSN", "전공/NNG", "입학/NNG", "하/XSV", "면/EC", "미술/NNG", "심리/NNG", "상담/NNG", "사/XSN", "자격/NNG", "증/XSN", "취득/NNG"], ["부산디지털대학교/NNP", "(/SS", "총장/NNG", "양상백/NNG", ")/SS", "평생/NNG", "교육/NNG", "원/XSN", "에서/JKB", "지나/VV", "ㄴ/ETM", "5/SN", "월/NNB", "8/SN", "일/NNB", "부터/JX", "2019/SN", "년/NNB", "사상구/NNP", "평생/NNG", "학습/NNG", "충전/NNG", "소/XSN", "지정/NNG", "운영/NNG", "사업/NNG", "에/JKB", "\"/SS", "성인/NNG", "여성/NNG", "우울/NNG", "증/XSN", "완화/NNG", "를/JKO", "위하/VV", "ㄴ/ETM", "'/SS", "미술/NNG", "심리/NNG", "상담/NNG", "사/XSN", "'/SS", "양성/NNG", "과정/NNG", "\"/SS", "을/JKO", "진행/NNG", "하/XSV", "고/EC", "있/VX", "다/EF"], ["21/SN", "세기/NNG", "현대/NNG", "사회/NNG", "에/JKB", "증가/NNG", "하/XSV", "고/EC", "있/VX", "는/ETM", "성인/NNG", "우울/NNG", "은/JX", "이제/MAG", "사회/NNG", "적/XSN", "이/VCP", "ㄴ/ETM", "문제/NNG", "로/JKB", "대두/NNG", "되/XSV", "었/EP", "다/EF"], ["이러하/VA", "ㄴ/ETM", "여성/NNG", "의/JKG", "우울/NNG", "증/XSN", "을/JKO", "완화/NNG", "하/XSV", "기/ETN", "위하/VV", "어서/EC", "는/JX", "지역/NNG", "사회/NNG", "에/JKB", "심리/NNG", "치료/NNG", "를/JKO", "담당/NNG", "하/XSV", "ㄹ/ETM", "수/NNB", "있/VA", "는/ETM", "전문/NNG", "가/XSN", "를/JKO", "양성/NNG", "을/JKO", "위하/VV", "어/EC", "사상/NNP", "구/NNG", "와/JC", "부산디지털대학교/NNP", "평생/NNG", "교육/NNG", "원/XSN", "와/JC", "미술/NNG", "치료/NNG", "학과/NNG", "가/JKS", "협력/NNG", "하/XSV", "어/EC", "미술/NNG", "심리/NNG", "상담/NNG", "사/XSN", "양성/NNG", "과정/NNG", "을/JKO", "운영/NNG", "하/XSV", "고/EC", "있/VX", "다/EF"], ["보/VV", "ㄴ/ETM", "양성/NNG", "과정/NNG", "은/JX", "미술/NNG", "치료/NNG", "분야/NNG", "전반/NNG", "에/JKB", "대하/VV", "ㄴ/ETM", "체계/NNG", "적/XSN", "이/VCP", "ㄴ/ETM", "이해/NNG", "를/JKO", "바탕/NNG", "으로/JKB", "이론/NNG", "과/JC", "실무/NNG", "를/JKO", "겸하/VV", "고/EC", "있/VX", "으며/EC", "현장/NNG", "경험/NNG", "이/JKS", "풍부하/VA", "ㄴ/ETM", "교수/NNG", "진/XSN", "을/JKO", "중심/NNG", "으로/JKB", "각종/NNG", "현장/NNG", "에서/JKB", "능동/NNG", "적/XSN", "으로/JKB", "대응/NNG", "하/XSV", "ㄹ/ETM", "수/NNB", "있/VA", "는/ETM", "전문/NNG", "인력/NNG", "을/JKO", "양성/NNG", "하/XSV", "는/ETM", "데/NNB", "에/JKB", "적극/NNG", "힘쓰/VV", "고/EC", "있/VX", "다/EF"], ["평생/NNG", "교육/NNG", "원/XSN", "과/JC", "미술/NNG", "치료학과/NNG", "의/JKG", "전폭/NNG", "적/XSN", "이/VCP", "ㄴ/ETM", "지원/NNG", "과/JC", "체계/NNG", "적/XSN", "이/VCP", "ㄴ/ETM", "커리큘럼/NNG", "을/JKO", "바탕/NNG", "으로/JKB", "최소/NNG", "2/SN", "개/NNB", "이상/NNG", "의/JKG", "미술/NNG", "심리/NNG", "상담/NNG", "관련/NNG", "자격/NNG", "증/XSN", "을/JKO", "취득/NNG", "하/XSV", "ㄹ/ETM", "수/NNB", "있/VA", "고/EC", ",/SP", "과정/NNG", "을/JKO", "이수/NNG", "하/XSV", "ㄴ/ETM", "후/NNG", "에/JKB", "는/JX", "동아리/NNG", "형태/NNG", "로/JKB", "지속/NNG", "적/XSN", "이/VCP", "ㄴ/ETM", "정보/NNG", "교환/NNG", "과/JC", "미술/NNG", "치료/NNG", "활동/NNG", "을/JKO", "하/VV", "ㄹ/ETM", "수/NNB", "있/VA", "게/EC", "되/VV", "ㄴ다/EF"], ["부산디지털대학교/NNP", "미술/NNG", "치료/NNG", "학/XSN", "과/JC", "이진/NNP", "영학과장/NNG", "은/JX", "\"/SS", "우리/NP", "지역/NNG", "사회/NNG", "에/JKB", "정신/NNG", "건강/NNG", "을/JKO", "이끌/VV", "어/EC", "가/VX", "ㄹ/ETM", "전문/NNG", "인력/NNG", "을/JKO", "양성/NNG", "하/XSV", "ㄴ다는/ETM", "것/NNB", "이/JKS", "자부/NNG", "심/XSN", "\"/SS", "이/VCP", "라며/EC", "\"/SS", "현장/NNG", "중심/NNG", "의/JKG", "실무/NNG", "형/XSN", "인재/NNG", "양성/NNG", "을/JKO", "위하/VV", "어/EC", "교수/NNG", "진/XSN", "들/XSN", "은/JX", "실제/NNG", "치료/NNG", "장면/NNG", "에서/JKB", "자신/NNG", "감/XSN", "을/JKO", "가지/VV", "ㄹ/ETM", "수/NNB", "있/VA", "도록/EC", "양성/NNG", "과정/NNG", "을/JKO", "이끌/VV", "어/EC", "가/VX", "고/EC", "있/VX", "다/EF", "\"/SS", "고/JKQ", "전하/VV", "었/EP", "다/EF"], ["부산디지털대학교/NNP", "미술/NNG", "치료학과/NNG", "의/JKG", "신/NNG", "편입/NNG", "생/XSN", "모집/NNG", "은/JX", "오/VV", "는/ETM", "8/SN", "월/NNB", "20/SN", "일/NNB", "까지/JX", "이/VCP", "며/EC", "부산디지털대학교/NNP", "입학/NNG", "지원/NNG", "센터/NNG", "에서/JKB", "지원/NNG", "서/NNG", "작성/NNG", "이/JKS", "가능/NNG", "하/XSA", "다/EF"], ["디지털/NNG", "본부/NNG", "news/SL", "@/SW", "busancom/SL"]], "tgt": [["부산디지털대학교/NNP", "(/SS", "총장/NNG", "양상백/NNG", ")/SS", "평생/NNG", "교육/NNG", "원/XSN", "에서/JKB", "지나/VV", "ㄴ/ETM", "5/SN", "월/NNB", "8/SN", "일/NNB", "부터/JX", "2019/SN", "년/NNB", "사상구/NNP", "평생/NNG", "학습/NNG", "충전/NNG", "소/XSN", "지정/NNG", "운영/NNG", "사업/NNG", "에/JKB", "\"/SS", "성인/NNG", "여성/NNG", "우울/NNG", "증/XSN", "완화/NNG", "를/JKO", "위하/VV", "ㄴ/ETM", "'/SS", "미술/NNG", "심리/NNG", "상담/NNG", "사/XSN", "'/SS", "양성/NNG", "과정/NNG", "\"/SS", "을/JKO", "진행/NNG", "하/XSV", "고/EC", "있/VX", "다/EF"], ["평생/NNG", "교육/NNG", "원/XSN", "과/JC", "미술/NNG", "치료학과/NNG", "의/JKG", "전폭/NNG", "적/XSN", "이/VCP", "ㄴ/ETM", "지원/NNG", "과/JC", "체계/NNG", "적/XSN", "이/VCP", "ㄴ/ETM", "커리큘럼/NNG", "을/JKO", "바탕/NNG", "으로/JKB", "최소/NNG", "2/SN", "개/NNB", "이상/NNG", "의/JKG", "미술/NNG", "심리/NNG", "상담/NNG", "관련/NNG", "자격/NNG", "증/XSN", "을/JKO", "취득/NNG", "하/XSV", "ㄹ/ETM", "수/NNB", "있/VA", "고/EC", ",/SP", "과정/NNG", "을/JKO", "이수/NNG", "하/XSV", "ㄴ/ETM", "후/NNG", "에/JKB", "는/JX", "동아리/NNG", "형태/NNG", "로/JKB", "지속/NNG", "적/XSN", "이/VCP", "ㄴ/ETM", "정보/NNG", "교환/NNG", "과/JC", "미술/NNG", "치료/NNG", "활동/NNG", "을/JKO", "하/VV", "ㄹ/ETM", "수/NNB", "있/VA", "게/EC", "되/VV", "ㄴ다/EF"], ["부산디지털대학교/NNP", "미술/NNG", "치료/NNG", "학/XSN", "과/JC", "이진/NNP", "영학과장/NNG", "은/JX", "\"/SS", "우리/NP", "지역/NNG", "사회/NNG", "에/JKB", "정신/NNG", "건강/NNG", "을/JKO", "이끌/VV", "어/EC", "가/VX", "ㄹ/ETM", "전문/NNG", "인력/NNG", "을/JKO", "양성/NNG", "하/XSV", "ㄴ다는/ETM", "것/NNB", "이/JKS", "자부/NNG", "심/XSN", "\"/SS", "이/VCP", "라며/EC", "\"/SS", "현장/NNG", "중심/NNG", "의/JKG", "실무/NNG", "형/XSN", "인재/NNG", "양성/NNG", "을/JKO", "위하/VV", "어/EC", "교수/NNG", "진/XSN", "들/XSN", "은/JX", "실제/NNG", "치료/NNG", "장면/NNG", "에서/JKB", "자신/NNG", "감/XSN", "을/JKO", "가지/VV", "ㄹ/ETM", "수/NNB", "있/VA", "도록/EC", "양성/NNG", "과정/NNG", "을/JKO", "이끌/VV", "어/EC", "가/VX", "고/EC", "있/VX", "다/EF", "\"/SS", "고/JKQ", "전하/VV", "었/EP", "다/EF"]]}]